Workbook

Sheet Annahmen
A1: Annahmen
A2: Blaue Zellen sind Eingaben. Alle anderen Blätter rechnen daraus.
A3: Grundstück und Bau
A4: Grundstück (m²) | B4: 960 | C4: Baufeld 3, ca. 960 m²
A5: Preis je m² (€) | B5: 230
A6: Grunderwerbsteuer | B6: 0.05 | C6: Steuer beim Grundstückskauf
A7: Notar und Grundbuch | B7: 0.02 | C7: Annahme
A8: Bruttogrundfläche BGF (m²) | B8: 1540 | C8: EG 540 + 1. OG 540 + Staffelgeschoss 460 (Holzbau)
A9: Baukosten je m² BGF (€) | B9: 2200 | C9: Annahme des Bauherrn (Bekanntenpreis), Angebot nötig
A10: Baunebenkosten | B10: 0.15 | C10: Architekt, Statik, Gebühren
A11: Gastro-Ausbau (€) | B11: 150000 | C11: Annahme des Bauherrn, einfacher Ausbau (erste Schätzung 310.000 €)
A12: Förderung (Zuschuss in % der Kosten) | B12: 0 | C12: Annahme, mit der Stadt klären (0 bis 25 %)
A14: Finanzierung
A15: Zins Plan | B15: 0.033 | C15: Mischzins aus Förderkrediten (Annahme)
A16: Zins Ausgang | B16: 0.04 | C16: 10 Jahre fest, Stand 17.09.2026
A17: Zins für diese Rechnung | B17: =B15 | C17: Auf =B16 stellen für den Ausgangszins
A18: Tilgung | B18: 0.01 | C18: Rückzahlung der Schuld, 0 % = nur Zinsen
A19: Bauzeit (Monate) | B19: 15 | C19: Plan im Blatt Kredit ist auf 15 Monate ausgelegt
A20: Bereitstellungszins p. a. | B20: 0.03 | C20: Gebühr auf zugesagtes, noch nicht abgerufenes Geld
A21: Bereitstellungszins ab Monat | B21: 7
A22: Raten-Aufschub (Monate) | B22: 12 | C22: Plan im Blatt Kredit ist auf 12 Monate ausgelegt
A24: Einnahmen und Gastro
A25: Wohnfläche (m²) | B25: 725 | C25: 8 Wohnungen: 5 × 83 m² im 1. OG, 3 × 103 m² im Staffelgeschoss
A26: Kaltmiete je m² Wohnfläche (€) | B26: =950/85 | C26: 950 € für 85 m² (Annahme des Bauherrn), Markt ca. 11 €/m²
A27: Gastrofläche (m²) | B27: 460
A28: Pacht je m² (€) | B28: 12 | C28: Gastro zahlt an das Haus
A29: Rücklagen | B29: 0.1 | C29: Reparaturen, Leerstand, in % von Miete und Pacht
A30: Gastro-Umsatz pro Monat (€) | B30: 50000 | C30: netto
A31: Gastro-Marge vor Pacht | B31: 0.305 | C31: Branchen-Richtwert
A32: Dein Lohn pro Monat (€) | B32: 0 | C32: wird vorerst nicht gerechnet
A34: Holzbau und Terrasse
A35: Staffelgeschoss in Holzbau (m² BGF) | B35: 460 | C35: Zimmerei, schmale Terrasse (0,8 m) rundum
A36: Holzbau günstiger als Massivbau (€ je m²) | B36: 400 | C36: Annahme, Angebot der Zimmerei nötig
A37: Dachterrasse rundum (m²) | B37: 72 | C37: zählt nicht zur BGF
A38: Terrasse Preis (€ je m²) | B38: 450 | C38: Abdichtung, Holzrost, Geländer, Annahme
A39: Preisnachlass Bauunternehmer/Zimmerei (%) | B39: 0 | C39: Bekanntenpreis, noch offen (z. B. 5 % oder 10 %)
A41: Büro im EG
A42: Büro-Fläche (m²) | B42: 0 | C42: in Variante B kein Büro, Gastro nutzt das ganze EG
A43: Büro-Miete je m² (€) | B43: 10 | C43: Annahme

Sheet Kosten
A1: Kosten bis zum fertigen Haus
A3: Posten | B3: Betrag | C3: Rechnung
A4: Grundstück | B4: =Annahmen!B4*Annahmen!B5 | C4: m² × Preis
A5: Grunderwerbsteuer | B5: =B4*Annahmen!B6
A6: Notar und Grundbuch | B6: =B4*Annahmen!B7
A7: Grundstück gesamt | B7: =SUM(B4:B6)
A8: Bau | B8: =(Annahmen!B8*Annahmen!B9-Annahmen!B35*Annahmen!B36+Annahmen!B37*Annahmen!B38)*(1-Annahmen!B39) | C8: BGF × Baukosten, minus Holz-Abschlag, plus Terrasse, minus Nachlass
A9: Baunebenkosten | B9: =B8*Annahmen!B10
A10: Bau gesamt | B10: =B8+B9
A11: Gastro-Ausbau | B11: =Annahmen!B11
A12: Gesamtkosten | B12: =B7+B10+B11
A13: Förderung (Zuschuss) | B13: =-B12*Annahmen!B12
A14: Kosten nach Förderung | B14: =B12+B13
A15: Kosten je m² BGF | B15: =B14/Annahmen!B8
A17: Grundstück nach Förderung (für den Kredit) | B17: =B7*(1-Annahmen!B12)
A18: Bau und Gastro nach Förderung (für den Kredit) | B18: =(B10+B11)*(1-Annahmen!B12)

Sheet Kredit
A1: Kredit: Bauzeit, Aufschub und Rate
A2: Zinsen und Bereitstellungszinsen werden dem Kredit zugeschlagen (kein Eigenkapital).
A4: Monat | B4: Auszahlung | C4: Zinsen | D4: Bereitstellung | E4: Noch nicht abgerufen | F4: Kredit am Monatsende | H4: Ergebnis
A5: 0 | B5: =Kosten!B17 | C5: 0 | D5: 0 | E5: =Kosten!B18 | F5: =B5 | H5: Zinsen in der Bauzeit | I5: =SUM(C6:C20)
A6: 1 | B6: =Kosten!$B$18/Annahmen!$B$19 | C6: =F5*Annahmen!$B$17/12 | D6: =IF(A6>=Annahmen!$B$21,E6*Annahmen!$B$20/12,0) | E6: =Kosten!B18 | F6: =F5+C6+D6+B6 | H6: Bereitstellungszinsen | I6: =SUM(D6:D20)
A7: 2 | B7: =Kosten!$B$18/Annahmen!$B$19 | C7: =F6*Annahmen!$B$17/12 | D7: =IF(A7>=Annahmen!$B$21,E7*Annahmen!$B$20/12,0) | E7: =E6-B6 | F7: =F6+C7+D7+B7 | H7: Zinsen im Aufschub-Jahr | I7: =SUM(C24:C35)
A8: 3 | B8: =Kosten!$B$18/Annahmen!$B$19 | C8: =F7*Annahmen!$B$17/12 | D8: =IF(A8>=Annahmen!$B$21,E8*Annahmen!$B$20/12,0) | E8: =E7-B7 | F8: =F7+C8+D8+B8 | H8: Kredit bei Start der Rate | I8: =F35
A9: 4 | B9: =Kosten!$B$18/Annahmen!$B$19 | C9: =F8*Annahmen!$B$17/12 | D9: =IF(A9>=Annahmen!$B$21,E9*Annahmen!$B$20/12,0) | E9: =E8-B8 | F9: =F8+C9+D9+B9 | H9: Rate pro Monat | I9: =F35*(Annahmen!B17+Annahmen!B18)/12
A10: 5 | B10: =Kosten!$B$18/Annahmen!$B$19 | C10: =F9*Annahmen!$B$17/12 | D10: =IF(A10>=Annahmen!$B$21,E10*Annahmen!$B$20/12,0) | E10: =E9-B9 | F10: =F9+C10+D10+B10 | H10: davon Zinsen | I10: =F35*Annahmen!B17/12
A11: 6 | B11: =Kosten!$B$18/Annahmen!$B$19 | C11: =F10*Annahmen!$B$17/12 | D11: =IF(A11>=Annahmen!$B$21,E11*Annahmen!$B$20/12,0) | E11: =E10-B10 | F11: =F10+C11+D11+B11 | H11: davon Tilgung | I11: =F35*Annahmen!B18/12
A12: 7 | B12: =Kosten!$B$18/Annahmen!$B$19 | C12: =F11*Annahmen!$B$17/12 | D12: =IF(A12>=Annahmen!$B$21,E12*Annahmen!$B$20/12,0) | E12: =E11-B11 | F12: =F11+C12+D12+B12
A13: 8 | B13: =Kosten!$B$18/Annahmen!$B$19 | C13: =F12*Annahmen!$B$17/12 | D13: =IF(A13>=Annahmen!$B$21,E13*Annahmen!$B$20/12,0) | E13: =E12-B12 | F13: =F12+C13+D13+B13
A14: 9 | B14: =Kosten!$B$18/Annahmen!$B$19 | C14: =F13*Annahmen!$B$17/12 | D14: =IF(A14>=Annahmen!$B$21,E14*Annahmen!$B$20/12,0) | E14: =E13-B13 | F14: =F13+C14+D14+B14
A15: 10 | B15: =Kosten!$B$18/Annahmen!$B$19 | C15: =F14*Annahmen!$B$17/12 | D15: =IF(A15>=Annahmen!$B$21,E15*Annahmen!$B$20/12,0) | E15: =E14-B14 | F15: =F14+C15+D15+B15
A16: 11 | B16: =Kosten!$B$18/Annahmen!$B$19 | C16: =F15*Annahmen!$B$17/12 | D16: =IF(A16>=Annahmen!$B$21,E16*Annahmen!$B$20/12,0) | E16: =E15-B15 | F16: =F15+C16+D16+B16
A17: 12 | B17: =Kosten!$B$18/Annahmen!$B$19 | C17: =F16*Annahmen!$B$17/12 | D17: =IF(A17>=Annahmen!$B$21,E17*Annahmen!$B$20/12,0) | E17: =E16-B16 | F17: =F16+C17+D17+B17
A18: 13 | B18: =Kosten!$B$18/Annahmen!$B$19 | C18: =F17*Annahmen!$B$17/12 | D18: =IF(A18>=Annahmen!$B$21,E18*Annahmen!$B$20/12,0) | E18: =E17-B17 | F18: =F17+C18+D18+B18
A19: 14 | B19: =Kosten!$B$18/Annahmen!$B$19 | C19: =F18*Annahmen!$B$17/12 | D19: =IF(A19>=Annahmen!$B$21,E19*Annahmen!$B$20/12,0) | E19: =E18-B18 | F19: =F18+C19+D19+B19
A20: 15 | B20: =Kosten!$B$18/Annahmen!$B$19 | C20: =F19*Annahmen!$B$17/12 | D20: =IF(A20>=Annahmen!$B$21,E20*Annahmen!$B$20/12,0) | E20: =E19-B19 | F20: =F19+C20+D20+B20
A22: Raten-Aufschub: nur Zinsen laufen auf
A23: Monat | C23: Zinsen | F23: Kredit am Monatsende
A24: 1 | C24: =F20*Annahmen!$B$17/12 | F24: =F20+C24
A25: 2 | C25: =F24*Annahmen!$B$17/12 | F25: =F24+C25
A26: 3 | C26: =F25*Annahmen!$B$17/12 | F26: =F25+C26
A27: 4 | C27: =F26*Annahmen!$B$17/12 | F27: =F26+C27
A28: 5 | C28: =F27*Annahmen!$B$17/12 | F28: =F27+C28
A29: 6 | C29: =F28*Annahmen!$B$17/12 | F29: =F28+C29
A30: 7 | C30: =F29*Annahmen!$B$17/12 | F30: =F29+C30
A31: 8 | C31: =F30*Annahmen!$B$17/12 | F31: =F30+C31
A32: 9 | C32: =F31*Annahmen!$B$17/12 | F32: =F31+C32
A33: 10 | C33: =F32*Annahmen!$B$17/12 | F33: =F32+C33
A34: 11 | C34: =F33*Annahmen!$B$17/12 | F34: =F33+C34
A35: 12 | C35: =F34*Annahmen!$B$17/12 | F35: =F34+C35

Sheet Cashflow
A1: Was pro Monat übrig bleibt
A2: Mit den Annahmen aus dem Blatt Annahmen (Zins, Förderung, Umsatz).
A4: Posten | B4: pro Monat
A5: Wohnungen und Büro (Kaltmiete) | B5: =Annahmen!B25*Annahmen!B26+Annahmen!B42*Annahmen!B43
A6: Gastro-Pacht | B6: =Annahmen!B27*Annahmen!B28
A7: Miete und Pacht gesamt | B7: =B5+B6
A8: Gastro-Gewinn nach Pacht | B8: =Annahmen!B30*Annahmen!B31-B6
A9: Rate (Zinsen und Tilgung) | B9: =-Kredit!I9
A10: Dein Lohn | B10: =-Annahmen!B32
A11: Rücklagen | B11: =-B7*Annahmen!B29
A12: Ergebnis pro Monat | B12: =B5+B6+B8+B9+B10+B11
A13: Ergebnis pro Jahr | B13: =B12*12
A15: Break-even Gastro-Umsatz (Ergebnis = 0, abzüglich Lohn aus Annahmen) | B15: =(Annahmen!B32+Kredit!I9+B7*Annahmen!B29-B7+B6)/Annahmen!B31
A17: Die Tilgung in der Rate ist Vermögensaufbau (die Schuld sinkt), kein Verlust.

Sheet Szenarien
A1: Szenarien (Werte aus dem Rechenmodell, Stand Oktober 2026)
A2: Gastro-Umsatz 50.000 €, Mieten 6 × 950 €. Ändern sich die Annahmen, bitte neu erzeugen.
A4: Förderung | B4: Gesamtkosten | C4: Rate Plan 3,3 % | D4: Ergebnis Plan | E4: Rate Ausgang 4,0 % | F4: Ergebnis Ausgang | G4: Break-even Umsatz Plan | H4: Break-even Umsatz Ausgang
A5: 0 | B5: 4108116 | C5: 15639.22 | D5: 6351.43 | E5: 18392.63 | F5: 3598.01 | G5: 29175.64 | H5: 38203.23
A6: 0.05 | B6: 3902710.2 | C6: 14857.26 | D6: 7133.39 | E6: 17473 | F6: 4517.65 | G6: 26611.83 | H6: 35188.05
A7: 0.1 | B7: 3697304.4 | C7: 14075.3 | D7: 7915.35 | E7: 16553.37 | F7: 5437.28 | G7: 24048.03 | H7: 32172.86
A8: 0.15 | B8: 3491898.6 | C8: 13293.33 | D8: 8697.31 | E8: 15633.74 | F8: 6356.91 | G8: 21484.22 | H8: 29157.68
A9: 0.2 | B9: 3286492.8 | C9: 12511.37 | D9: 9479.27 | E9: 14714.11 | F9: 7276.54 | G9: 18920.42 | H9: 26142.49
A10: 0.25 | B10: 3081087 | C10: 11729.41 | D10: 10261.23 | E10: 13794.48 | F10: 8196.17 | G10: 16356.61 | H10: 23127.31
A12: Ergebnis pro Monat (ohne Lohn des Bauherrn), Plan 3,3 %, je Gastro-Umsatz
A13: Förderung | B13: 40.000 € | C13: 45.000 € | D13: 50.000 € | E13: 55.000 € | F13: 60.000 €
A14: 0 | B14: 3301.43 | C14: 4826.43 | D14: 6351.43 | E14: 7876.43 | F14: 9401.43
A15: 0.1 | B15: 4865.35 | C15: 6390.35 | D15: 7915.35 | E15: 9440.35 | F15: 10965.35
A16: 0.15 | B16: 5647.31 | C16: 7172.31 | D16: 8697.31 | E16: 10222.31 | F16: 11747.31
A17: 0.2 | B17: 6429.27 | C17: 7954.27 | D17: 9479.27 | E17: 11004.27 | F17: 12529.27

Sheet Verkauf je Partei
A1: Verkauf an die Familie: Rechnung je Partei
A2: Jede Partei mit eigenem Kredit ohne Eigenkapital. Preis = Selbstkosten, 3,3 % Zins, 1 % Tilgung, 10 % Rücklagen. Feste Werte aus model.js.
B4: A: 1. OG 85 m² | C4: A: Staffel 63 m² | D4: A: Gastro (Du) | E4: B: 1. OG 83 m² | F4: B: Staffel 103 m² | G4: B: Gastro (Du) | H4: C: Regelgeschoss 83 m² | I4: C: Staffel 103 m² | J4: C: Gastro + Büro (Du)
A5: Preis (Selbstkosten) | B5: 314624.67 | C5: 226174.33 | D5: 1093874 | E5: 289808.6 | F5: 353343.32 | G5: 1599043 | H5: 142753.57 | I5: 347236.31 | J5: 1577535.7
A6: Rate pro Monat | B6: 1197.75 | C6: 861.02 | D6: 4164.28 | E6: 1103.27 | F6: 1345.15 | G6: 6087.41 | H6: 543.45 | I6: 1321.9 | J6: 6005.53
A7: Einnahme nach Rücklagen / Gastro-Gewinn (+ Büro) | B7: 855 | C7: 633.71 | D7: 15250 | E7: 834.88 | F7: 1039.41 | G7: 15250 | H7: 417.44 | I7: 1039.41 | J7: 15250
A8: Ergebnis pro Monat | B8: -342.75 | C8: -227.32 | D8: 11085.72 | E8: -268.39 | F8: -305.73 | G8: 9162.59 | H8: -126.01 | I8: -282.48 | J8: 9244.47
A9: Preis für Ergebnis 0 € | B9: 211401.81 | C9: 156686.04 | E9: 206427.65 | F9: 256998.27 | H9: 103213.82 | I9: 256998.27
A10: Lücke zum Selbstkostenpreis | B10: 103222.86 | C10: 69488.29 | E10: 83380.96 | F10: 96345.05 | H10: 39539.75 | I10: 90238.03
A13: Haus als Ganzes mit einem Kredit
B14: A: 340 m² | C14: B (Haupt): 540 m² | D14: C: 540 m², 3 Vollgeschosse + Holz-Penthouse
A15: Gesamtkosten | B15: 2716271 | C15: 4108116 | D15: 5474316
A16: Rate pro Monat | B16: 10345.03 | C16: 15639.22 | D16: 20835.86
A17: Ergebnis pro Monat bei 50.000 € Umsatz | B17: 9686.97 | C17: 6351.43 | D17: 5329.2
A18: Break-even Gastro-Umsatz | B18: 18239.43 | C18: 29175.64 | D18: 32527.22
A20: B (Hauptvariante): EG 540 m² (Gastro 460), 1. OG 540 m², Staffel 460 m² mit 72 m² Terrasse. C: zusätzlich 2. OG 540 m², Höhe ca. 13 m. Nur mit Ausnahme der Stadt (Baufenster, II Vollgeschosse, 12 m).
A22: Ziel: 250 € Plus je Wohnung (Käufer ohne Eigenkapital, ohne Tilgung, Variante B)
B23: 1. OG 83 m² | C23: Staffel 103 m² | D23: Du | E23: Zins 4,0 %: 1. OG | F23: Zins 4,0 %: Staffel | G23: Zins 4,0 %: Du
A24: Verkaufspreis | B24: 200194 | C24: 270200 | E24: 163297 | F24: 220400
A25: Selbstkosten | B25: 289808.6 | C25: 353343.32 | E25: 289808.6 | F25: 353343.32
A26: Nachlass (von dir getragen) | B26: 89614.6 | C26: 83143.32 | D26: 697502.99 | E26: 126511.6 | F26: 132943.32 | G26: 1031388
A27: Rate pro Monat | B27: 584.88 | C27: 789.41 | D27: 8125.22 | E27: 584.88 | F27: 789.41 | G27: 10853.29
A28: Ergebnis pro Monat | B28: 250 | C28: 250 | D28: 7124.78 | E28: 250 | F28: 250 | G28: 4396.71
A31: Verkaufsplan (Vorschlag), ohne Förderung, 2.200 €/m², tilgungsfrei, 3,3 % Zins, Notar 2 %, Grunderwerbsteuer 5 % (Vater frei)
A32: Partei | B32: Wohnung | C32: Verkaufspreis | D32: Selbstkosten | E32: Differenz (von dir getragen) | F32: Notar, Steuer | G32: Rate (nur Zinsen) | H32: Ergebnis pro Monat | I32: Ergebnis zum Selbstkostenpreis
A33: Vater | B33: 1. OG, 83 m² | C33: 246603.85 | D33: 289808.6 | E33: 43204.76 | F33: 4932.08 | G33: 734.88 | H33: 100 | I33: -28.75
A34: Bruder | B34: 1. OG, 83 m² | C34: 235080.3 | D34: 289808.6 | E34: 54728.3 | F34: 16455.62 | G34: 734.88 | H34: 100 | I34: -71.09
A35: Du (Wohnung 1, eigene) | B35: 1. OG, 83 m² | C35: 289808.6 | D35: 289808.6 | E35: 0 | F35: 0 | G35: 846.7 | H35: -11.82 | I35: -11.82
A36: Du (Wohnung 2, vermietet) | B36: 1. OG, 83 m² | C36: 289808.6 | D36: 289808.6 | E36: 0 | F36: 0 | G36: 846.7 | H36: -11.82 | I36: -11.82
A37: Du (Wohnung 3, vermietet) | B37: 1. OG, 83 m² | C37: 289808.6 | D37: 289808.6 | E37: 0 | F37: 0 | G37: 846.7 | H37: -11.82 | I37: -11.82
A38: Onkel 1 | B38: Staffel, 103 m² | C38: 300506.88 | D38: 353343.32 | E38: 52836.45 | F38: 21035.48 | G38: 939.41 | H38: 100 | I38: -65.17
A39: Onkel 2 | B39: Staffel, 103 m² | C39: 300506.88 | D39: 353343.32 | E39: 52836.45 | F39: 21035.48 | G39: 939.41 | H39: 100 | I39: -65.17
A40: Onkel 3 | B40: Staffel, 103 m² | C40: 300506.88 | D40: 353343.32 | E40: 52836.45 | F40: 21035.48 | G40: 939.41 | H40: 100 | I40: -65.17
A42: Differenz gesamt (von dir getragen) | C42: 256442.4
A43: Zinsen auf die Differenz pro Monat | C43: 749.22
A44: Dein Ergebnis pro Monat (Gastro − Rate EG − Zinsen Differenz + deine drei Wohnungen) | C44: 8377.92

Sheet Variante 4 Ebenen
A1: Variante: Mittelgeschoss doppelt (4 Ebenen, Basis Variante A)
A2: Nur als Gedankenspiel: Höhe ca. 13 m, der B-Plan erlaubt 12 m.
B4: 3 Ebenen | C4: 4 Ebenen
A5: Wohnungen | B5: 6 | C5: 9
A6: BGF (m²) | B6: 960 | C6: 1300
A7: Gesamtkosten | B7: 2716271 | C7: 3576471
A8: Rate (Plan) | B8: 10345.03 | C8: 13616.99
A9: Ergebnis pro Monat ohne Förderung | B9: 9686.97 | C9: 8980.01
A10: Ergebnis pro Monat mit 15 % Förderung | B10: 11238.73 | C10: 11022.56

Sheet Hinweise
A1: Hinweise und offene Punkte
A3: • Alle Zahlen sind Planungsannahmen, keine Zusagen von Bank oder Stadt.
A4: • Nebenkosten (Grundsteuer, Gebäudeversicherung, Betriebskosten) werden auf die Mieter umgelegt. Hausverwaltung und Instandhaltung sind nicht umlagefähig und stecken in der Rücklage von 10 %.
A5: • Miete 11,18 €/m² (950 € für 85 m²) liegt am oberen Rand der Portalwerte für Neubau in Werlte (ca. 10,70–11,02 €/m²).
A6: • Förderung ist als Zuschuss in Prozent der Gesamtkosten angesetzt, Höhe und Zweck sind offen.
A7: • Gastro-Marge (30,5 % vor Pacht) und Kostenstruktur sind Branchen-Richtwerte, nicht aus Werlte.
A8: • Grundfläche 540 m² (Baufenster im Plan geschätzt kleiner), Staffelgeschoss (ca. 460 m², Holzbau, schmale Terrasse rundum) und Gesamthöhe ca. 9,90 m müssen mit der Stadt abgestimmt werden.
A9: • Zinsbindung 10 Jahre, der Folgezins ist offen.
