Workbook

Sheet Übersicht
A1: Wirtschaftlichkeit Gesamtkonzept Neue Mitte Werlte, Baufeld 3 (Arbeitsgrundlage B3)
A2: Ergebnis der Prüfung: ohne Förderung in keinem Szenario tragfähig. Alle Werte Annahmen; keine Förderzusage; Architektur, Wirtschaftlichkeit und baurechtliche Machbarkeit getrennt zu bewerten.
A4: Größe (Eigenkapital 20 %) | B4: vorsichtig | C4: realistisch | D4: günstig | E4: Hinweis
A5: Gesamtkosten | B5: =Rechenkern!C31 -> 8411875.4 | C5: =Rechenkern!D31 -> 6641738.7 | D5: =Rechenkern!E31 -> 5524199
A6: Eigenkapital | B6: =Rechenkern!C34 -> 1682375.1 | C6: =Rechenkern!D34 -> 1328347.7 | D6: =Rechenkern!E34 -> 1104839.8
A7: Fremdkapital | B7: =Rechenkern!C33 -> 6729500.3 | C7: =Rechenkern!D33 -> 5313390.9 | D7: =Rechenkern!E33 -> 4419359.2
A8: Zinsbelastung monatlich | B8: =Rechenkern!C39 -> 27478.793 | C8: =Rechenkern!D39 -> 19925.216 | D8: =Rechenkern!E39 -> 15099.477
A9: Kreditrate monatlich (Zins + 2 % Tilgung) | B9: =Rechenkern!C38 -> 38694.627 | C9: =Rechenkern!D38 -> 28780.868 | D9: =Rechenkern!E38 -> 22465.076
A10: Kapitaldienst jährlich | B10: =Rechenkern!C37 -> 464335.52 | C10: =Rechenkern!D37 -> 345370.41 | D10: =Rechenkern!E37 -> 269580.91
A11: Mieteinnahmen nach Leerstand jährlich | B11: =Rechenkern!C47 -> 136035.09 | C11: =Rechenkern!D47 -> 159732.52 | D11: =Rechenkern!E47 -> 182975.08
A12: laufende Kosten jährlich | B12: =Rechenkern!C51 -> 28701.966 | C12: =Rechenkern!D51 -> 22886.514 | D12: =Rechenkern!E51 -> 19386.808
A13: Netto-Mietertrag jährlich | B13: =Rechenkern!C52 -> 107333.13 | C13: =Rechenkern!D52 -> 136846.01 | D13: =Rechenkern!E52 -> 163588.27
A14: Cashflow nach Kapitaldienst jährlich | B14: =Rechenkern!C53 -> -357002.4 | C14: =Rechenkern!D53 -> -208524.4 | D14: =Rechenkern!E53 -> -105992.64
A15: Kapitaldienstdeckungsgrad | B15: =Rechenkern!C55 -> 0.23115424 | C15: =Rechenkern!D55 -> 0.39622968 | D15: =Rechenkern!E55 -> 0.60682439
A16: Nettoanfangsrendite | B16: =Rechenkern!C56 -> 0.012759714 | C16: =Rechenkern!D56 -> 0.020603944 | D16: =Rechenkern!E56 -> 0.02961303
A17: Break-even Wohnmiete für DSCR 1,0 (€/m²) | B17: =Rechenkern!C57 -> 46.13399 | C17: =Rechenkern!D57 -> 31.568645 | D17: =Rechenkern!E57 -> 22.100438
A18: Break-even Faktor aller Mieten für DSCR 1,0 | B18: =Rechenkern!C59 -> 3.6618985 | C18: =Rechenkern!D59 -> 2.3201431 | D18: =Rechenkern!E59 -> 1.5849042
A19: nötiges Eigenkapital für DSCR 1,2 | B19: =Rechenkern!C63 -> 6695187.2 | C19: =Rechenkern!D63 -> 4671541 | D19: =Rechenkern!E63 -> 3189170.5
A20: DSCR mit KfW 297 + 299 (theoretisch, nicht zugesagt) | B20: =Rechenkern!C69 -> 0.25363737 | C20: =Rechenkern!D69 -> 0.45455573 | D20: =Rechenkern!E69 -> 0.78708408
A21: Bewertung (rechnerisch) | B21: =IF(B15>=1.2,"tragfähig",IF(B15>=1,"knapp","NICHT tragfähig")) -> NICHT tragfähig | C21: =IF(C15>=1.2,"tragfähig",IF(C15>=1,"knapp","NICHT tragfähig")) -> NICHT tragfähig | D21: =IF(D15>=1.2,"tragfähig",IF(D15>=1,"knapp","NICHT tragfähig")) -> NICHT tragfähig | E21: DSCR ab 1,2 gilt üblicherweise als tragfähig (Annahme); hier weit darunter.
A23: Konsistenzprüfung (Blatt Prüfung): | B23: =Prüfung!D12 -> TRUE

Sheet Annahmen
A1: Annahmen
A2: Alle Eingaben (blau). Spalten D–F: vorsichtig / realistisch / günstig. Stand 22.10.2026. Status je Zeile: Geometrie, Vorgabe, Annahme, Quelle, noch zu bestätigen.
B4: Parameter | C4: Einheit | D4: vorsichtig | E4: realistisch | F4: günstig | G4: Status | H4: Quelle / Begründung
B5: FLÄCHEN (aus der Geometrie B3, Variante K)
A6: bgf_eg | B6: Bruttogrundfläche Erdgeschoss | C6: m² | D6: 576 | E6: 576 | F6: 576 | G6: Geometrie | H6: variants3_metrics.json
A7: bgf_l1 | B7: Bruttogrundfläche 1. Obergeschoss | C7: m² | D7: 660 | E7: 660 | F7: 660 | G7: Geometrie | H7: variants3_metrics.json
A8: bgf_l2 | B8: Bruttogrundfläche Staffelgeschoss | C8: m² | D8: 539.06 | E8: 539.06 | F8: 539.06 | G8: Geometrie | H8: variants3_metrics.json
A9: wfl | B9: Wohnfläche netto (16 Wohnungen, Brutto × 0,88) | C9: m² | D9: 845.93 | E9: 845.93 | F9: 845.93 | G9: Geometrie, Annahme Netto-Faktor 0,88 | H9: Balkone und Dachterrassen nicht angerechnet (WoFlV-Anrechnung 25–50 % nicht angesetzt, konservativ)
A10: we | B10: Anzahl Wohnungen | C10: Stk | D10: 16 | E10: 16 | F10: 16 | G10: Geometrie
A11: gastro_nf | B11: Gastronomie Mietfläche (Gastraum, Bar, Küche, Lager, WC, Personal, Flur, Anlieferung) | C11: m² | D11: 440 | E11: 440 | F11: 440 | G11: Geometrie | H11: Gastraum 280 m² für ca. 120 Innenplätze (möbliert), Terrasse 44 Plätze
A12: buero_nf | B12: Büros vermietbare Nettofläche (2 Büros ohne Foyer und WC) | C12: m² | D12: 56.32 | E12: 56.32 | F12: 56.32 | G12: Geometrie | H12: Foyer und Büro-WC (15,6 m²) nicht als Mietfläche angesetzt
A13: gew_bgf | B13: Gewerbe-Bruttofläche im EG (Gastro 440 + Büro 64) | C13: m² | D13: 504 | E13: 504 | F13: 504 | G13: Geometrie
B14: GRUNDSTÜCK UND ERWERBSNEBENKOSTEN (KG 100)
A15: gr_m2 | B15: Grundstücksfläche | C15: m² | D15: 960 | E15: 960 | F15: 960 | G15: Vorgabe | H15: Projektangaben
A16: gr_preis | B16: Kaufpreis | C16: €/m² | D16: 230 | E16: 230 | F16: 230 | G16: Vorgabe | H16: Projektangaben
A17: grest | B17: Grunderwerbsteuer Niedersachsen | C17: % | D17: 5 | E17: 5 | F17: 5 | G17: Annahme (gesetzlicher Satz zu prüfen)
A18: notar | B18: Notar, Grundbuch | C18: % | D18: 2 | E18: 2 | F18: 2 | G18: Annahme | H18: übliche Spanne 1,5–2 %
B19: BAUKOSTEN (KG 200–500), Preise brutto inkl. 19 % MwSt, Vorsteuerabzug nicht angesetzt
A20: kg200 | B20: KG 200 Herrichten und Erschließen (Pauschale) | C20: € | D20: 60000 | E20: 40000 | F20: 25000 | G20: Annahme, kein Bodengutachten | H20: Grundstückszustand und Anschlüsse unbekannt
A21: bau_m2 | B21: KG 300+400 Bauwerk je m² BGF | C21: €/m² | D21: 3000 | E21: 2500 | F21: 2200 | G21: Annahme | H21: Orientierung: MFH 2.500–3.500 €/m² Wohnfläche (Ratgeberseiten, nicht BKI); günstig = bisherige Projektannahme 2.200 €/m² BGF
A22: eh40 | B22: Aufschlag Effizienzhaus 40 / QNG-Nachweis auf KG 300+400 | C22: % | D22: 4 | E22: 3 | F22: 2 | G22: Annahme | H22: Programm- und Nachweisanforderungen KfW 297, noch nicht gerechnet
A23: ausbau | B23: Gewerbe: Ausbau durch Vermieter (Haustechnik-Anschlüsse, Abluft, Fettabscheider, Rohausbau) | C23: €/m² Gewerbe-BGF | D23: 300 | E23: 250 | F23: 200 | G23: Annahme | H23: Mieterausbau und Küche durch den Betreiber
A24: kg500_m2 | B24: KG 500 Außenanlagen, Stellplätze, Hof je m² (hypothetisch 384 m²) | C24: €/m² | D24: 200 | E24: 160 | F24: 130 | G24: Annahme, HYPOTHETISCH | H24: Fläche aus der Hypothese Grundstück 32 × 30 m, nicht bestätigt
A25: kg500_fl | B25: Fläche Außenanlagen (hypothetisch) | C25: m² | D25: 384 | E25: 384 | F25: 384 | G25: HYPOTHETISCH | H25: 32 × 12 m Rückbereich
A26: kg500_terr | B26: Terrasse und Stahlvordach am Platz (Pauschale) | C26: € | D26: 50000 | E26: 40000 | F26: 30000 | G26: Annahme | H26: Lage und Eigentum ungeprüft
B27: BAUNEBENKOSTEN (KG 700) in % von KG 300–500
A28: bnk_arch | B28: Architektur und Objektplanung (HOAI-Leistungsphasen 1–8) | C28: % | D28: 13 | E28: 12 | F28: 11 | G28: Annahme
A29: bnk_fach | B29: Fachplaner: Statik, TGA, Brandschutz, Energieberatung, QNG-Zertifizierung | C29: % | D29: 6.5 | E29: 5.5 | F29: 4.5 | G29: Annahme
A30: bnk_gen | B30: Genehmigungen, Gutachten, Vermessung, Bodengutachten | C30: % | D30: 1.5 | E30: 1.2 | F30: 1 | G30: Annahme
A31: bnk_son | B31: Bauleitung extern, Versicherungen, Sonstiges | C31: % | D31: 1.5 | E31: 1.2 | F31: 1 | G31: Annahme
A32: reserve | B32: Reserve für Unvorhergesehenes in % von KG 200–500 | C32: % | D32: 8 | E32: 6 | F32: 4 | G32: Annahme
B33: FINANZIERUNGSKOSTEN
A34: bauzeit | B34: Bauzeit | C34: Monate | D34: 15 | E34: 15 | F34: 15 | G34: Projektannahme
A35: abruf | B35: mittlere Inanspruchnahme des Kredits in der Bauzeit | C35: % | D35: 50 | E35: 50 | F35: 50 | G35: Annahme
A36: anlauf | B36: Vermietungsanlauf ohne Mieteinnahmen (Zinsen laufen) | C36: Monate | D36: 9 | E36: 6 | F36: 3 | G36: Annahme
A37: bearb | B37: Bearbeitung, Bereitstellung, Bewertung | C37: % des Kredits | D37: 1 | E37: 1 | F37: 1 | G37: Annahme
B38: ZINSEN UND TILGUNG
A39: z_bank | B39: Zinssatz Hausbank (10 Jahre fest, gewerbliche Mischfinanzierung) | C39: % | D39: 4.9 | E39: 4.5 | F39: 4.1 | G39: Annahme | H39: Bauzinsen 10/2026 für 10 Jahre ca. 4,0–4,5 % (Dr. Klein 22.10.2026: 4,13 % eff.; Interhyp 4,42 %; Sparkasse 4,45 %); Aufschlag gewerblich/Mischnutzung
A40: z_297 | B40: Zinssatz KfW 297/298 (Wohngebäude) | C40: % | D40: 3.5 | E40: 3 | F40: 2 | G40: noch zu bestätigen | H40: Quellen widersprüchlich: 0,6 % (März 2026), 1,96 % (01.10.2026), 3,05 % (EH 40, KfW 29.09.2026 laut Drittseite)
A41: z_299 | B41: Zinssatz KfW 299 (Nichtwohngebäude) | C41: % | D41: 3.9 | E41: 3.4 | F41: 2.6 | G41: noch zu bestätigen | H41: kein Zinssatz gefunden; Annahme Aufschlag auf 297
A42: tilg | B42: anfängliche Tilgung | C42: % p. a. | D42: 2 | E42: 2 | F42: 2 | G42: Annahme | H42: Variante 1 % wird zusätzlich ausgewiesen
B43: MIETEN UND LEERSTAND (netto kalt, ohne Umsatzsteuer)
A44: m_wohn | B44: Wohnungen Sollmiete | C44: €/m² Monat | D44: 9.5 | E44: 10.5 | F44: 11.5 | G44: Annahme | H44: Angebote Werlte/Emsland 2026 (Kleinanzeigen, Immowelt, Meinestadt), Mietspiegel Werlte 7,78–8,43 €/m² (ImmoScout24, miet-check, miete-aktuell); Neubau-Angebote 9,5–12,5 €/m²
A45: v_wohn | B45: Wohnungen Leerstand und Mietausfall | C45: % | D45: 4 | E45: 2.5 | F45: 1.5 | G45: Annahme
A46: m_gastro | B46: Gastronomie Pachtmiete | C46: €/m² Monat | D46: 8 | E46: 10 | F46: 12 | G46: Annahme (keine belastbare Vergleichsquelle) | H46: Kontrolle über Umsatzquote 8–12 % (Ratgeber, nicht regional belegt)
A47: v_gastro | B47: Gastronomie Mietausfall | C47: % | D47: 8 | E47: 5 | F47: 3 | G47: Annahme | H47: Betreiberwechsel, Anlaufzeit
A48: m_buero | B48: Büros Miete | C48: €/m² Monat | D48: 8.5 | E48: 9.5 | F48: 10.5 | G48: Annahme | H48: Angebote Werlte 9,6–12 €/m² (kleine Einheiten), Meppen 9–9,5, Sögel 6,3–7,8
A49: v_buero | B49: Büros Leerstand | C49: % | D49: 20 | E49: 12 | F49: 8 | G49: Annahme | H49: kleine Büroeinheiten in Kleinstadt, Vermietbarkeit ungeprüft
B50: LAUFENDE KOSTEN (nicht umlagefähig)
A51: ih_wohn | B51: Instandhaltung Wohnen | C51: €/m² WF Jahr | D51: 12 | E51: 10 | F51: 9 | G51: Annahme
A52: vw_wohn | B52: Verwaltung Wohnen | C52: €/Wohnung Jahr | D52: 350 | E52: 300 | F52: 250 | G52: Annahme
A53: nu_wohn | B53: sonstige nicht umlagefähige Kosten Wohnen (Leerstandskosten, Aufzug anteilig) | C53: €/m² WF Jahr | D53: 6 | E53: 4 | F53: 3 | G53: Annahme
A54: ih_gew | B54: Instandhaltung Gewerbe | C54: €/m² Jahr | D54: 8 | E54: 6 | F54: 5 | G54: Annahme
A55: vw_gew | B55: Verwaltung Gewerbe | C55: % der Miete | D55: 4 | E55: 3 | F55: 2.5 | G55: Annahme
A56: nu_gew | B56: sonstige nicht umlagefähige Kosten Gewerbe | C56: €/m² Jahr | D56: 4 | E56: 3 | F56: 2 | G56: Annahme
B57: FÖRDERUNG (theoretische Obergrenzen, nicht bestätigt)
A58: kfw297_we | B58: KfW 297 Kreditobergrenze je Wohneinheit (mit QNG-PLUS/PREMIUM) | C58: € | D58: 150000 | E58: 150000 | F58: 150000 | G58: Quelle (Drittseiten, Merkblatt nicht abrufbar) | H58: 100.000 € ohne, 150.000 € mit QNG-PLUS/-PREMIUM
A59: kfw299_m2 | B59: KfW 299 Kreditobergrenze je m² (nicht zertifiziert) | C59: €/m² | D59: 1500 | E59: 1500 | F59: 1500 | G59: Quelle (Drittseite), Bezugsfläche ungeklärt | H59: 2.000 €/m² mit QNG, 1.000 €/m² bei EG 55; Merkblatt 07/2026 nicht abrufbar
A60: nb_zusch | B60: NBank Mietwohnraum: Zuschuss in % der förderfähigen Kosten (Obergrenze) | C60: % | D60: 40 | E60: 40 | F60: 40 | G60: Quelle (NBank-Pressemeldung 07/2026), Höhe je Fall ungeklärt | H60: Obergrenze, bei niedrigem Einkommen bis 80 % Gesamtförderung
A61: nb_miete | B61: NBank gebundene Miete (Mietstufe I–III, mittlere Einkommen) | C61: €/m² Monat | D61: 7.8 | E61: 7.8 | F61: 7.8 | G61: Quelle Stand 04/2026, evtl. überholt | H61: Mietstufe Werlte unbekannt
A62: nb_cap | B62: NBank Kostengrenze | C62: €/m² WF | D62: 5330 | E62: 5330 | F62: 5330 | G62: Quelle Stand 04/2026, evtl. überholt

Sheet Flächen
A1: Flächen- und Wohnungsübersicht (Geometrie B3, Variante K)
A2: Quelle: geometry/variant_B3.json. Netto = Brutto × 0,88 (Annahme). Alle Flächen hypothetisch bis zur Freigabe; Balkone und Dachterrassen nicht in der Wohnfläche.
A4: Nr. | B4: Geschoss | C4: Typ | D4: Brutto m² | E4: Netto m² | F4: Sollmiete €/Monat (realistisch) | G4: Außenraum | H4: Bemerkung
A5: 1.01 | B5: 1. OG | C5: 1. OG vorn, Studio | D5: 53.2 | E5: =D5*0.88 -> 46.816 | F5: =E5*Annahmen!$E$44 -> 491.568 | G5: Balkon 2,70 × 1,50 m
A6: 1.02 | B6: 1. OG | C6: 1. OG vorn, Studio | D6: 53.2 | E6: =D6*0.88 -> 46.816 | F6: =E6*Annahmen!$E$44 -> 491.568 | G6: Balkon 2,70 × 1,50 m
A7: 1.03 | B7: 1. OG | C7: 1. OG vorn, Studio | D7: 53.2 | E7: =D7*0.88 -> 46.816 | F7: =E7*Annahmen!$E$44 -> 491.568 | G7: Balkon 2,70 × 1,50 m
A8: 1.04 | B8: 1. OG | C8: 1. OG vorn, Studio | D8: 53.2 | E8: =D8*0.88 -> 46.816 | F8: =E8*Annahmen!$E$44 -> 491.568 | G8: Balkon 2,70 × 1,50 m
A9: 1.05 | B9: 1. OG | C9: 1. OG vorn, Studio | D9: 53.2 | E9: =D9*0.88 -> 46.816 | F9: =E9*Annahmen!$E$44 -> 491.568 | G9: Balkon 2,70 × 1,50 m
A10: 1.06 | B10: 1. OG | C10: 1. OG hinten, Zweizimmer | D10: 66.5 | E10: =D10*0.88 -> 58.52 | F10: =E10*Annahmen!$E$44 -> 614.46 | G10: –
A11: 1.07 | B11: 1. OG | C11: 1. OG hinten, Zweizimmer | D11: 66.5 | E11: =D11*0.88 -> 58.52 | F11: =E11*Annahmen!$E$44 -> 614.46 | G11: –
A12: 1.08 | B12: 1. OG | C12: 1. OG hinten, Zweizimmer | D12: 66.5 | E12: =D12*0.88 -> 58.52 | F12: =E12*Annahmen!$E$44 -> 614.46 | G12: –
A13: 1.09 | B13: 1. OG | C13: 1. OG hinten, Zweizimmer | D13: 66.5 | E13: =D13*0.88 -> 58.52 | F13: =E13*Annahmen!$E$44 -> 614.46 | G13: –
A14: 3.01 | B14: Staffel | C14: 3. Geschoss vorn, Zweizimmer | D14: 58.72 | E14: =D14*0.88 -> 51.6736 | F14: =E14*Annahmen!$E$44 -> 542.5728 | G14: Umlauf 0,80 m
A15: 3.02 | B15: Staffel | C15: 3. Geschoss vorn, Zweizimmer | D15: 58.72 | E15: =D15*0.88 -> 51.6736 | F15: =E15*Annahmen!$E$44 -> 542.5728 | G15: Umlauf 0,80 m
A16: 3.03 | B16: Staffel | C16: 3. Geschoss vorn, Zweizimmer | D16: 58.72 | E16: =D16*0.88 -> 51.6736 | F16: =E16*Annahmen!$E$44 -> 542.5728 | G16: Umlauf 0,80 m
... A20: 3.07 | B20: Staffel | C20: 3. Geschoss hinten, Zweizimmer | D20: 64.8 | E20: =D20*0.88 -> 57.024 | F20: =E20*Annahmen!$E$44 -> 598.752 | G20: Dachterrasse 20,7 m²
A21: Summe 16 Wohnungen | D21: =SUM(D5:D20) -> 961.28 | E21: =SUM(E5:E20) -> 845.9264 | F21: =SUM(F5:F20) -> 8882.2272
A23: Nutzungsflächen
A24: Bereich | D24: Brutto m² | E24: Netto / Mietfläche m² | H24: Bemerkung
A25: Gastronomie (Gastraum 280, Küche 60, Lager 27, WC 24, Personal 20, Flur 20, Anlieferung 9) | D25: 440 | E25: 440 | H25: ca. 120 Innenplätze möbliert, 44 Terrassenplätze
A26: Büros 1 und 2 (je 32 m² brutto) | D26: 64 | E26: 56.3 | H26: ohne Foyer und Büro-WC (15,6 m²)
A27: Büro-Foyer und Büro-WC (Alternative K) | D27: 15.6 | E27: 0 | H27: keine Mietfläche
A28: Wohnkern EG (Halle, Treppe, Flur, Aufzug, Technik) | D28: 56.4 | E28: 0 | H28: Erschließung Wohnen
A29: Wohnungen 1. OG | D29: 660 | E29: 468 | H29: inklusive Kern, Gang
A30: Wohnungen Staffelgeschoss | D30: 539.06 | E30: 377.8 | H30: inklusive Kern, Gang
A31: Bruttogeschossfläche gesamt (EG 576 + 1. OG 660 + Staffel 539,06) | D31: =Annahmen!E6+Annahmen!E7+Annahmen!E8 -> 1775.06
A33: Hinweis: Die Geschossflächen (Auskragung 3,00 m, Staffel 1,50 m) sind hypothetisch; Baufenster, GRZ und Abstände sind ungeklärt (C-30).

Sheet Einnahmen
A1: Einnahmen und laufende Kosten (Eigenkapital 20 %, Szenarien)
A2: Getrennte Einnahmebereiche. Mieten netto kalt ohne Umsatzsteuer. Gastronomie als Vermietung an einen Betreiber, kein eigener Restaurantbetrieb.
A4: Position | B4: vorsichtig | C4: realistisch | D4: günstig | E4: Hinweis
A5: A. GASTRONOMIE
A6: Mietfläche m² | B6: =INDEX(Annahmen!$D$11:$F$11,1) -> 440 | C6: =INDEX(Annahmen!$D$11:$F$11,2) -> 440 | D6: =INDEX(Annahmen!$D$11:$F$11,3) -> 440
A7: Miete €/m² Monat | B7: =INDEX(Annahmen!$D$46:$F$46,1) -> 8 | C7: =INDEX(Annahmen!$D$46:$F$46,2) -> 10 | D7: =INDEX(Annahmen!$D$46:$F$46,3) -> 12
A8: Sollmiete monatlich | B8: =Rechenkern!C41/12 -> 3520 | C8: =Rechenkern!D41/12 -> 4400 | D8: =Rechenkern!E41/12 -> 5280
A9: Sollmiete jährlich | B9: =Rechenkern!C41 -> 42240 | C9: =Rechenkern!D41 -> 52800 | D9: =Rechenkern!E41 -> 63360
A10: Mietausfall % | B10: =INDEX(Annahmen!$D$47:$F$47,1) -> 8 | C10: =INDEX(Annahmen!$D$47:$F$47,2) -> 5 | D10: =INDEX(Annahmen!$D$47:$F$47,3) -> 3
A11: Einnahmen nach Ausfall jährlich | B11: =Rechenkern!C45 -> 38860.8 | C11: =Rechenkern!D45 -> 50160 | D11: =Rechenkern!E45 -> 61459.2
A12: B. WOHNUNGEN (16)
A13: Wohnfläche m² | B13: =INDEX(Annahmen!$D$9:$F$9,1) -> 845.93 | C13: =INDEX(Annahmen!$D$9:$F$9,2) -> 845.93 | D13: =INDEX(Annahmen!$D$9:$F$9,3) -> 845.93
A14: Miete €/m² Monat | B14: =INDEX(Annahmen!$D$44:$F$44,1) -> 9.5 | C14: =INDEX(Annahmen!$D$44:$F$44,2) -> 10.5 | D14: =INDEX(Annahmen!$D$44:$F$44,3) -> 11.5
A15: Sollmiete monatlich | B15: =Rechenkern!C40/12 -> 8036.335 | C15: =Rechenkern!D40/12 -> 8882.265 | D15: =Rechenkern!E40/12 -> 9728.195
A16: Sollmiete jährlich | B16: =Rechenkern!C40 -> 96436.02 | C16: =Rechenkern!D40 -> 106587.18 | D16: =Rechenkern!E40 -> 116738.34
A17: Leerstand und Mietausfall % | B17: =INDEX(Annahmen!$D$45:$F$45,1) -> 4 | C17: =INDEX(Annahmen!$D$45:$F$45,2) -> 2.5 | D17: =INDEX(Annahmen!$D$45:$F$45,3) -> 1.5
A18: Einnahmen nach Leerstand jährlich | B18: =Rechenkern!C44 -> 92578.579 | C18: =Rechenkern!D44 -> 103922.5 | D18: =Rechenkern!E44 -> 114987.26
A19: C. BÜROS (2)
A20: vermietbare Nettofläche m² | B20: =INDEX(Annahmen!$D$12:$F$12,1) -> 56.32 | C20: =INDEX(Annahmen!$D$12:$F$12,2) -> 56.32 | D20: =INDEX(Annahmen!$D$12:$F$12,3) -> 56.32
A21: Miete €/m² Monat | B21: =INDEX(Annahmen!$D$48:$F$48,1) -> 8.5 | C21: =INDEX(Annahmen!$D$48:$F$48,2) -> 9.5 | D21: =INDEX(Annahmen!$D$48:$F$48,3) -> 10.5
A22: Sollmiete monatlich | B22: =Rechenkern!C42/12 -> 478.72 | C22: =Rechenkern!D42/12 -> 535.04 | D22: =Rechenkern!E42/12 -> 591.36
A23: Sollmiete jährlich | B23: =Rechenkern!C42 -> 5744.64 | C23: =Rechenkern!D42 -> 6420.48 | D23: =Rechenkern!E42 -> 7096.32
A24: Leerstand % | B24: =INDEX(Annahmen!$D$49:$F$49,1) -> 20 | C24: =INDEX(Annahmen!$D$49:$F$49,2) -> 12 | D24: =INDEX(Annahmen!$D$49:$F$49,3) -> 8
A25: Einnahmen nach Leerstand jährlich | B25: =Rechenkern!C46 -> 4595.712 | C25: =Rechenkern!D46 -> 5650.0224 | D25: =Rechenkern!E46 -> 6528.6144
A26: GESAMT
A27: Sollmiete jährlich | B27: =Rechenkern!C43 -> 144420.66 | C27: =Rechenkern!D43 -> 165807.66 | D27: =Rechenkern!E43 -> 187194.66
A28: Sollmiete monatlich | B28: =Rechenkern!C43/12 -> 12035.055 | C28: =Rechenkern!D43/12 -> 13817.305 | D28: =Rechenkern!E43/12 -> 15599.555
A29: Einnahmen nach Leerstand jährlich | B29: =Rechenkern!C47 -> 136035.09 | C29: =Rechenkern!D47 -> 159732.52 | D29: =Rechenkern!E47 -> 182975.08
A30: nicht umlagefähige Kosten Wohnen (Instandhaltung, Verwaltung, sonstige) | B30: =Rechenkern!C48 -> 20826.74 | C30: =Rechenkern!D48 -> 16643.02 | D30: =Rechenkern!E48 -> 14151.16
A31: Instandhaltung und sonstige Kosten Gewerbe | B31: =Rechenkern!C49 -> 5955.84 | C31: =Rechenkern!D49 -> 4466.88 | D31: =Rechenkern!E49 -> 3474.24
A32: Verwaltung Gewerbe | B32: =Rechenkern!C50 -> 1919.3856 | C32: =Rechenkern!D50 -> 1776.6144 | D32: =Rechenkern!E50 -> 1761.408
A33: laufende Kosten gesamt | B33: =Rechenkern!C51 -> 28701.966 | C33: =Rechenkern!D51 -> 22886.514 | D33: =Rechenkern!E51 -> 19386.808
A34: NETTO-MIETERTRAG jährlich | B34: =Rechenkern!C52 -> 107333.13 | C34: =Rechenkern!D52 -> 136846.01 | D34: =Rechenkern!E52 -> 163588.27
A35: Netto-Mietertrag monatlich | B35: =Rechenkern!C52/12 -> 8944.4271 | C35: =Rechenkern!D52/12 -> 11403.834 | D35: =Rechenkern!E52/12 -> 13632.356
A37: Kontrolle Gastronomie: Pachtmiete / Umsatz
A38: angenommener Jahresumsatz des Betreibers je Innenplatz (Annahme, nicht belegt) € | B38: 4000 | C38: 5500 | D38: 7000 | E38: Annahme: ländlicher Restaurantbetrieb, nicht regional belegt
A39: Plätze innen + Terrasse (möbliert normal 120 + 44) | B39: 164 | C39: 164 | D39: 164
A40: Pacht in % vom Umsatz (Richtwert Branche 8–12 %, Ratgeber) | B40: =B9/(B38*B39) -> 0.064390244 | C40: =C9/(C38*C39) -> 0.058536585 | D40: =D9/(D38*D39) -> 0.055191638

Sheet Kosten
A1: Kostenschätzung nach DIN 276 (Eigenkapital 20 %, Szenarien)
A2: Preise brutto inkl. 19 % MwSt, Vorsteuerabzug nicht angesetzt. Fehlende Kostendaten sind Annahmen (Blatt Annahmen). Ohne Bodengutachten und Lageplan.
A4: Kostengruppe | B4: vorsichtig | C4: realistisch | D4: günstig | E4: Hinweis
A5: KG 100 Grundstück (960 m² × 230 €/m²) | B5: =Rechenkern!C12 -> 220800 | C5: =Rechenkern!D12 -> 220800 | D5: =Rechenkern!E12 -> 220800
A6: Erwerbsnebenkosten (Grunderwerbsteuer 5 %, Notar und Grundbuch 2 %) | B6: =Rechenkern!C13 -> 15456 | C6: =Rechenkern!D13 -> 15456 | D6: =Rechenkern!E13 -> 15456
A7: KG 200 Herrichten und Erschließen | B7: =Rechenkern!C15 -> 60000 | C7: =Rechenkern!D15 -> 40000 | D7: =Rechenkern!E15 -> 25000 | E7: Pauschale, Grundstückszustand unbekannt
A8: KG 300+400 Bauwerk (Bau- und Technik) inkl. Effizienzhaus-40-Aufschlag | B8: =Rechenkern!C17 -> 5538187.2 | C8: =Rechenkern!D17 -> 4570779.5 | D8: =Rechenkern!E17 -> 3983234.6 | E8: BGF 1.775 m² × €/m²
A9: Gewerbe-Ausbau durch Vermieter (Anschlüsse, Abluft, Fettabscheider) | B9: =Rechenkern!C18 -> 151200 | C9: =Rechenkern!D18 -> 126000 | D9: =Rechenkern!E18 -> 100800 | E9: Betreiberküche und Mieterausbau durch Mieter
A10: KG 500 Außenanlagen, Stellplätze, Terrasse mit Vordach | B10: =Rechenkern!C19 -> 126800 | C10: =Rechenkern!D19 -> 101440 | D10: =Rechenkern!E19 -> 79920 | E10: HYPOTHETISCH (32 × 30 m)
A11: KG 700 Architektur und Objektplanung | B11: =Rechenkern!C21 -> 756104.34 | C11: =Rechenkern!D21 -> 575786.34 | D11: =Rechenkern!E21 -> 458035.01
A12: KG 700 Fachplaner: Statik, TGA, Brandschutz, Energieberatung, QNG | B12: =Rechenkern!C22 -> 378052.17 | C12: =Rechenkern!D22 -> 263902.07 | D12: =Rechenkern!E22 -> 187377.96
A13: KG 700 Genehmigungen, Gutachten, Vermessung | B13: =Rechenkern!C23 -> 87242.808 | C13: =Rechenkern!D23 -> 57578.634 | D13: =Rechenkern!E23 -> 41639.546
A14: KG 700 Bauleitung, Versicherungen, Sonstiges | B14: =Rechenkern!C24 -> 87242.808 | C14: =Rechenkern!D24 -> 57578.634 | D14: =Rechenkern!E24 -> 41639.546
A15: Reserve | B15: =Rechenkern!C26 -> 470094.98 | C15: =Rechenkern!D26 -> 290293.17 | D15: =Rechenkern!E26 -> 167558.19
A16: Zwischensumme ohne Finanzierungskosten | B16: =Rechenkern!C27 -> 7891180.3 | C16: =Rechenkern!D27 -> 6319614.4 | D16: =Rechenkern!E27 -> 5321460.9
A17: Finanzierungskosten (Bauzeitzinsen, Anlaufzinsen, Bereitstellung) | B17: =Rechenkern!C32 -> 520695.09 | C17: =Rechenkern!D32 -> 322124.33 | D17: =Rechenkern!E32 -> 202738.1 | E17: auf Fremdkapital mit Hausbankzins
A18: GESAMTKOSTEN | B18: =Rechenkern!C31 -> 8411875.4 | C18: =Rechenkern!D31 -> 6641738.7 | D18: =Rechenkern!E31 -> 5524199
A19: Gesamtkosten je m² BGF | B19: =Rechenkern!C31/Rechenkern!C16 -> 4738.9245 | C19: =Rechenkern!D31/Rechenkern!D16 -> 3741.6981 | D19: =Rechenkern!E31/Rechenkern!E16 -> 3112.1196
A20: Gesamtkosten je m² Nutzfläche (Wohnen + Gewerbe netto) | B20: =Rechenkern!C31/(INDEX(Annahmen!$D$9:$F$9,1)+INDEX(Annahmen!$D$11:$F$11,1)+INDEX(Annahmen!$D$12:$F$12,1)) -> 6266.996 | C20: =Rechenkern!D31/(INDEX(Annahmen!$D$9:$F$9,2)+INDEX(Annahmen!$D$11:$F$11,2)+INDEX(Annahmen!$D$12:$F$12,2)) -> 4948.2128 | D20: =Rechenkern!E31/(INDEX(Annahmen!$D$9:$F$9,3)+INDEX(Annahmen!$D$11:$F$11,3)+INDEX(Annahmen!$D$12:$F$12,3)) -> 4115.626
A22: Nicht enthalten: Mieterausbau, Küche und Inventar des Betreibers; KG 600; Umsatzsteuer-Option bei Gewerbe (Vorsteuer); Stellplatz-Ablöse; Fördermittel.

Sheet Finanzierung
A1: Finanzierung bei unterschiedlichen Eigenkapitalquoten (ohne Förderung)
A2: Zinsen und Tilgung im Jahr 1; Hausbank 10 Jahre fest. Eigenkapital = Anteil der Gesamtkosten inkl. Finanzierungskosten.
A4: Größe | B4: V 0 % | C4: V 10 % | D4: V 20 % | E4: V 30 % | F4: R 0 % | G4: R 10 % | H4: R 20 % | I4: R 30 % | J4: G 0 % | K4: G 10 % | L4: G 20 % | M4: G 30 %
A5: Gesamtkosten | B5: =Rechenkern!F31 -> 8552966 | C5: =Rechenkern!G31 -> 8481834 | D5: =Rechenkern!C31 -> 8411875.4 | E5: =Rechenkern!H31 -> 8343061.4 | F5: =Rechenkern!I31 -> 6727467 | G5: =Rechenkern!J31 -> 6684328 | H5: =Rechenkern!D31 -> 6641738.7 | I5: =Rechenkern!K31 -> 6599688.6 | J5: =Rechenkern!L31 -> 5577320.5 | K5: =Rechenkern!M31 -> 5550632.6 | L5: =Rechenkern!E31 -> 5524199 | M5: =Rechenkern!N31 -> 5498015.9
A6: Eigenkapital | B6: =Rechenkern!F34 -> 0 | C6: =Rechenkern!G34 -> 848183.4 | D6: =Rechenkern!C34 -> 1682375.1 | E6: =Rechenkern!H34 -> 2502918.4 | F6: =Rechenkern!I34 -> 0 | G6: =Rechenkern!J34 -> 668432.8 | H6: =Rechenkern!D34 -> 1328347.7 | I6: =Rechenkern!K34 -> 1979906.6 | J6: =Rechenkern!L34 -> 0 | K6: =Rechenkern!M34 -> 555063.26 | L6: =Rechenkern!E34 -> 1104839.8 | M6: =Rechenkern!N34 -> 1649404.8
A7: Fremdkapital | B7: =Rechenkern!F33 -> 8552966 | C7: =Rechenkern!G33 -> 7633650.6 | D7: =Rechenkern!C33 -> 6729500.3 | E7: =Rechenkern!H33 -> 5840142.9 | F7: =Rechenkern!I33 -> 6727467 | G7: =Rechenkern!J33 -> 6015895.2 | H7: =Rechenkern!D33 -> 5313390.9 | I7: =Rechenkern!K33 -> 4619782 | J7: =Rechenkern!L33 -> 5577320.5 | K7: =Rechenkern!M33 -> 4995569.4 | L7: =Rechenkern!E33 -> 4419359.2 | M7: =Rechenkern!N33 -> 3848611.1
A8: Zinssatz Hausbank % | B8: =Rechenkern!F28 -> 4.9 | C8: =Rechenkern!G28 -> 4.9 | D8: =Rechenkern!C28 -> 4.9 | E8: =Rechenkern!H28 -> 4.9 | F8: =Rechenkern!I28 -> 4.5 | G8: =Rechenkern!J28 -> 4.5 | H8: =Rechenkern!D28 -> 4.5 | I8: =Rechenkern!K28 -> 4.5 | J8: =Rechenkern!L28 -> 4.1 | K8: =Rechenkern!M28 -> 4.1 | L8: =Rechenkern!E28 -> 4.1 | M8: =Rechenkern!N28 -> 4.1
A9: Zinsbelastung monatlich | B9: =Rechenkern!F39 -> 34924.611 | C9: =Rechenkern!G39 -> 31170.74 | D9: =Rechenkern!C39 -> 27478.793 | E9: =Rechenkern!H39 -> 23847.25 | F9: =Rechenkern!I39 -> 25228.001 | G9: =Rechenkern!J39 -> 22559.607 | H9: =Rechenkern!D39 -> 19925.216 | I9: =Rechenkern!K39 -> 17324.183 | J9: =Rechenkern!L39 -> 19055.845 | K9: =Rechenkern!M39 -> 17068.195 | L9: =Rechenkern!E39 -> 15099.477 | M9: =Rechenkern!N39 -> 13149.421
A10: anfängliche Tilgung % | B10: =Rechenkern!F29 -> 2 | C10: =Rechenkern!G29 -> 2 | D10: =Rechenkern!C29 -> 2 | E10: =Rechenkern!H29 -> 2 | F10: =Rechenkern!I29 -> 2 | G10: =Rechenkern!J29 -> 2 | H10: =Rechenkern!D29 -> 2 | I10: =Rechenkern!K29 -> 2 | J10: =Rechenkern!L29 -> 2 | K10: =Rechenkern!M29 -> 2 | L10: =Rechenkern!E29 -> 2 | M10: =Rechenkern!N29 -> 2
A11: Kreditrate monatlich | B11: =Rechenkern!F38 -> 49179.555 | C11: =Rechenkern!G38 -> 43893.491 | D11: =Rechenkern!C38 -> 38694.627 | E11: =Rechenkern!H38 -> 33580.822 | F11: =Rechenkern!I38 -> 36440.446 | G11: =Rechenkern!J38 -> 32586.099 | H11: =Rechenkern!D38 -> 28780.868 | I11: =Rechenkern!K38 -> 25023.819 | J11: =Rechenkern!L38 -> 28351.379 | K11: =Rechenkern!M38 -> 25394.144 | L11: =Rechenkern!E38 -> 22465.076 | M11: =Rechenkern!N38 -> 19563.773
A12: Kapitaldienst jährlich | B12: =Rechenkern!F37 -> 590154.66 | C12: =Rechenkern!G37 -> 526721.89 | D12: =Rechenkern!C37 -> 464335.52 | E12: =Rechenkern!H37 -> 402969.86 | F12: =Rechenkern!I37 -> 437285.36 | G12: =Rechenkern!J37 -> 391033.19 | H12: =Rechenkern!D37 -> 345370.41 | I12: =Rechenkern!K37 -> 300285.83 | J12: =Rechenkern!L37 -> 340216.55 | K12: =Rechenkern!M37 -> 304729.73 | L12: =Rechenkern!E37 -> 269580.91 | M12: =Rechenkern!N37 -> 234765.28
A13: Netto-Mietertrag jährlich | B13: =Rechenkern!F52 -> 107333.13 | C13: =Rechenkern!G52 -> 107333.13 | D13: =Rechenkern!C52 -> 107333.13 | E13: =Rechenkern!H52 -> 107333.13 | F13: =Rechenkern!I52 -> 136846.01 | G13: =Rechenkern!J52 -> 136846.01 | H13: =Rechenkern!D52 -> 136846.01 | I13: =Rechenkern!K52 -> 136846.01 | J13: =Rechenkern!L52 -> 163588.27 | K13: =Rechenkern!M52 -> 163588.27 | L13: =Rechenkern!E52 -> 163588.27 | M13: =Rechenkern!N52 -> 163588.27
A14: Cashflow nach Kapitaldienst jährlich | B14: =Rechenkern!F53 -> -482821.53 | C14: =Rechenkern!G53 -> -419388.77 | D14: =Rechenkern!C53 -> -357002.4 | E14: =Rechenkern!H53 -> -295636.74 | F14: =Rechenkern!I53 -> -300439.35 | G14: =Rechenkern!J53 -> -254187.18 | H14: =Rechenkern!D53 -> -208524.4 | I14: =Rechenkern!K53 -> -163439.82 | J14: =Rechenkern!L53 -> -176628.28 | K14: =Rechenkern!M53 -> -141141.46 | L14: =Rechenkern!E53 -> -105992.64 | M14: =Rechenkern!N53 -> -71177.009
A15: Cashflow nach Kapitaldienst monatlich | B15: =Rechenkern!F54 -> -40235.128 | C15: =Rechenkern!G54 -> -34949.064 | D15: =Rechenkern!C54 -> -29750.2 | E15: =Rechenkern!H54 -> -24636.395 | F15: =Rechenkern!I54 -> -25036.612 | G15: =Rechenkern!J54 -> -21182.265 | H15: =Rechenkern!D54 -> -17377.034 | I15: =Rechenkern!K54 -> -13619.985 | J15: =Rechenkern!L54 -> -14719.023 | K15: =Rechenkern!M54 -> -11761.788 | L15: =Rechenkern!E54 -> -8832.72 | M15: =Rechenkern!N54 -> -5931.4174
A16: Kapitaldienstdeckungsgrad | B16: =Rechenkern!F55 -> 0.18187288 | C16: =Rechenkern!G55 -> 0.20377571 | D16: =Rechenkern!C55 -> 0.23115424 | E16: =Rechenkern!H55 -> 0.26635522 | F16: =Rechenkern!I55 -> 0.31294441 | G16: =Rechenkern!J55 -> 0.34996009 | H16: =Rechenkern!D55 -> 0.39622968 | I16: =Rechenkern!K55 -> 0.45571916 | J16: =Rechenkern!L55 -> 0.48083573 | K16: =Rechenkern!M55 -> 0.53683069 | L16: =Rechenkern!E55 -> 0.60682439 | M16: =Rechenkern!N55 -> 0.69681629
A17: Nettoanfangsrendite | B17: =Rechenkern!F56 -> 0.012549229 | C17: =Rechenkern!G56 -> 0.012654471 | D17: =Rechenkern!C56 -> 0.012759714 | E17: =Rechenkern!H56 -> 0.012864957 | F17: =Rechenkern!I56 -> 0.020341387 | G17: =Rechenkern!J56 -> 0.020472665 | H17: =Rechenkern!D56 -> 0.020603944 | I17: =Rechenkern!K56 -> 0.020735222 | J17: =Rechenkern!L56 -> 0.029330979 | K17: =Rechenkern!M56 -> 0.029472005 | L17: =Rechenkern!E56 -> 0.02961303 | M17: =Rechenkern!N56 -> 0.029754056
A18: Bewertung (rechnerisch) | B18: =IF(B16>=1.2,"tragfähig",IF(B16>=1,"knapp","nicht tragfähig")) -> nicht tragfähig | C18: =IF(C16>=1.2,"tragfähig",IF(C16>=1,"knapp","nicht tragfähig")) -> nicht tragfähig | D18: =IF(D16>=1.2,"tragfähig",IF(D16>=1,"knapp","nicht tragfähig")) -> nicht tragfähig | E18: =IF(E16>=1.2,"tragfähig",IF(E16>=1,"knapp","nicht tragfähig")) -> nicht tragfähig | F18: =IF(F16>=1.2,"tragfähig",IF(F16>=1,"knapp","nicht tragfähig")) -> nicht tragfähig | G18: =IF(G16>=1.2,"tragfähig",IF(G16>=1,"knapp","nicht tragfähig")) -> nicht tragfähig | H18: =IF(H16>=1.2,"tragfähig",IF(H16>=1,"knapp","nicht tragfähig")) -> nicht tragfähig | I18: =IF(I16>=1.2,"tragfähig",IF(I16>=1,"knapp","nicht tragfähig")) -> nicht tragfähig | ... M18: =IF(M16>=1.2,"tragfähig",IF(M16>=1,"knapp","nicht tragfähig")) -> nicht tragfähig
A20: Kapitaldienst bei 1 % statt 2 % Tilgung (R, EK 20 %) | B20: =Rechenkern!O37 -> 292236.5 | C20: DSCR | D20: =Rechenkern!O55 -> 0.46827144
A21: Fremdkapital, das bei DSCR 1,2 tragbar wäre (R, EK 20 %) | B21: =Rechenkern!D61 -> 1754436 | C21: nötiges Eigenkapital | D21: =Rechenkern!D63 -> 4671541 | E21: Quote | F21: =Rechenkern!D62 -> 0.72697755
A22: Break-even Wohnmiete DSCR 1,0 / 1,2 (R, EK 20 %) €/m² | B22: =Rechenkern!D57 -> 31.568645 | C22: =Rechenkern!D58 -> 38.547671
A23: Break-even Faktor aller Mieten DSCR 1,0 / 1,2 (R, EK 20 %) | B23: =Rechenkern!D59 -> 2.3201431 | C23: =Rechenkern!D60 -> 2.7574429

Sheet Sensitivität
A1: Sensitivität (realistisches Szenario, Eigenkapital 20 %)
A2: Jede Spalte ist ein voller Rechenfall.
A4: Größe | B4: R 20 % | C4: R Baukosten +10 % | D4: R Baukosten +20 % | E4: R Zins +1 pp | F4: R Zins +2 pp | G4: R Leerstand +5 pp | H4: R Leerstand +10 pp | I4: R Miete −10 % | J4: R 20 %, Tilgung 1 %
A5: Gesamtkosten | B5: =Rechenkern!D31 -> 6641738.7 | C5: =Rechenkern!P31 -> 7246532.3 | D5: =Rechenkern!Q31 -> 7851325.9 | E5: =Rechenkern!R31 -> 6705161.1 | F5: =Rechenkern!S31 -> 6769806.5 | G5: =Rechenkern!T31 -> 6641738.7 | H5: =Rechenkern!U31 -> 6641738.7 | I5: =Rechenkern!V31 -> 6641738.7 | J5: =Rechenkern!O31 -> 6641738.7
A6: Fremdkapital | B6: =Rechenkern!D33 -> 5313390.9 | C6: =Rechenkern!P33 -> 5797225.8 | D6: =Rechenkern!Q33 -> 6281060.7 | E6: =Rechenkern!R33 -> 5364128.9 | F6: =Rechenkern!S33 -> 5415845.2 | G6: =Rechenkern!T33 -> 5313390.9 | H6: =Rechenkern!U33 -> 5313390.9 | I6: =Rechenkern!V33 -> 5313390.9 | J6: =Rechenkern!O33 -> 5313390.9
A7: Kapitaldienst jährlich | B7: =Rechenkern!D37 -> 345370.41 | C7: =Rechenkern!P37 -> 376819.68 | D7: =Rechenkern!Q37 -> 408268.95 | E7: =Rechenkern!R37 -> 402309.67 | F7: =Rechenkern!S37 -> 460346.84 | G7: =Rechenkern!T37 -> 345370.41 | H7: =Rechenkern!U37 -> 345370.41 | I7: =Rechenkern!V37 -> 345370.41 | J7: =Rechenkern!O37 -> 292236.5
A8: Netto-Mietertrag jährlich | B8: =Rechenkern!D52 -> 136846.01 | C8: =Rechenkern!P52 -> 136846.01 | D8: =Rechenkern!Q52 -> 136846.01 | E8: =Rechenkern!R52 -> 136846.01 | F8: =Rechenkern!S52 -> 136846.01 | G8: =Rechenkern!T52 -> 128555.63 | H8: =Rechenkern!U52 -> 120265.24 | I8: =Rechenkern!V52 -> 121050.42 | J8: =Rechenkern!O52 -> 136846.01
A9: Cashflow jährlich | B9: =Rechenkern!D53 -> -208524.4 | C9: =Rechenkern!P53 -> -239973.67 | D9: =Rechenkern!Q53 -> -271422.94 | E9: =Rechenkern!R53 -> -265463.66 | F9: =Rechenkern!S53 -> -323500.83 | G9: =Rechenkern!T53 -> -216814.79 | H9: =Rechenkern!U53 -> -225105.17 | I9: =Rechenkern!V53 -> -224319.99 | J9: =Rechenkern!O53 -> -155390.49
A10: Kapitaldienstdeckungsgrad | B10: =Rechenkern!D55 -> 0.39622968 | C10: =Rechenkern!P55 -> 0.36316046 | D10: =Rechenkern!Q55 -> 0.33518593 | E10: =Rechenkern!R55 -> 0.34015093 | F10: =Rechenkern!S55 -> 0.29726718 | G10: =Rechenkern!T55 -> 0.37222536 | H10: =Rechenkern!U55 -> 0.34822104 | I10: =Rechenkern!V55 -> 0.35049447 | J10: =Rechenkern!O55 -> 0.46827144
A11: Break-even Wohnmiete DSCR 1,0 €/m² | B11: =Rechenkern!D57 -> 31.568645 | C11: =Rechenkern!P57 -> 34.746179 | D11: =Rechenkern!Q57 -> 37.923713 | E11: =Rechenkern!R57 -> 37.321606 | F11: =Rechenkern!S57 -> 43.185499 | G11: =Rechenkern!T57 -> 33.590402 | H11: =Rechenkern!U57 -> 35.843217 | I11: =Rechenkern!V57 -> 32.114581 | J11: =Rechenkern!O57 -> 26.200163
A14: Bei allen Fällen liegt der Deckungsgrad unter 1,0: Die Aussage hängt nicht an einzelnen Annahmen.

Sheet Förderung
A1: Förderung: theoretische Kredithöhe und Einfluss auf die Finanzierung (realistisch, Eigenkapital 20 %)
A2: Unterscheidung: theoretisch möglich / fachlich plausibel / bestätigte Zusage (keine). Konditionen sind zeitabhängig; Zinssätze noch zu bestätigen. Abruf der Quellen 22.10.2026.
A4: Programm | B4: theoretisch möglich | C4: fachlich plausibel (Einschätzung) | D4: bestätigte Zusage | E4: theoretische Kredit-/Zuschusshöhe | F4: Bedingungen, Hinweise, Kombinationsausschluss
A5: KfW 297/298 Klimafreundlicher Neubau Wohngebäude | B5: ja (Wohnanteil ca. 72 % der BGF) | C5: plausibel, wenn Effizienzhaus 40 bzw. 55 mit QNG erreichbar; Misch-Nutzung zu prüfen | D5: keine | E5: =Rechenkern!D65 -> 2400000 | F5: bis 100.000 € je Wohneinheit, bis 150.000 € mit QNG-PLUS/-PREMIUM (16 WE: bis 2,4 Mio €); reine Zinsverbilligung ohne Tilgungszuschuss; Laufzeit bis 35 Jahre, Zinsbindung bis 10 Jahre; Effizienzhaus-55-Stufe befristet bis 31.12.2026 und mit begrenzten Bundesmitteln; Antrag vor Baubeginn; Zinssatz noch zu bestätigen
A6: KfW 296 Klimafreundlicher Neubau im Niedrigpreissegment | B6: nur wenn alle Programmkriterien erfüllt | C6: unwahrscheinlich: Kostengrenzen, Wohnflächenoptimierung und Lebenszykluskriterien, Gewerbeanteil und Dachterrassen nicht geprüft | D6: keine | E6: bis 100.000 € je Wohneinheit (16 WE: 1,6 Mio €) | F6: mindestens Effizienzhaus 55, Treibhausgasgrenze, keine fossile Wärme, Wohnflächenoptimierung nach WoFlV; nicht mit 297/298/299 für dieselbe Einheit kombinierbar; Merkblatt 06/2026 nicht abgerufen
A7: KfW 299 Klimafreundlicher Neubau Nichtwohngebäude (Gewerbeteil) | B7: ja für Gastronomie und Büros (Nichtwohnanteil ca. 28 %) | C7: unklar: Bezugsfläche, Mischnutzung und Abgrenzung zum Wohnteil sind zu klären | D7: keine | E7: =Rechenkern!D66 -> 756000 | F7: laut Drittseiten bis 1.500 €/m² (2.000 mit QNG, 1.000 bei Effizienzgebäude 55); Merkblatt 07/2026 (ab 30.07.2026) nicht abrufbar; 10 Jahre zweckentsprechende Nutzung; Antrag vor Baubeginn; Zinssatz nicht gefunden
A8: NBank Mietwohnraumförderung Neubau (Niedersachsen, seit 01.07.2026) | B8: ja für den Wohnteil (gebundene Mieten) | C8: nicht plausibel mit den Marktmieten: Mietbindung 35 Jahre, Mietstufe Werlte unbekannt | D8: keine | E8: =Rechenkern!D71 -> 1803522.8 | F8: Zuschuss bis 40 % der förderfähigen Kosten, bis 80 % Gesamtförderung bei niedrigen Einkommen (Pressemeldung); Obergrenzen je Wohnung nicht abgerufen; Miete 6,30–7,80 €/m² (Stand 04/2026), Effizienzhaus 40, mindestens 3 Wohnungen, Antrag vor Maßnahmenbeginn
A9: Kommunale Programme Werlte / Samtgemeinde Werlte | B9: nicht ermittelt | C9: nicht beurteilbar | D9: keine | E9: – | F9: bei der Stadt erfragen
A11: Einfluss auf die Finanzierung (theoretisch, nicht zugesagt)
A12: Größe | B12: ohne Förderung | C12: mit KfW 297 + 299 (theoretisch) | D12: mit NBank-Zuschuss (theoretisch) | F12: Bemerkung
A13: Fremdkapital | B13: =Rechenkern!D33 -> 5313390.9 | C13: =Rechenkern!D33 -> 5313390.9 | D13: =Rechenkern!D72 -> 3509868.2
A14: davon KfW | B14: 0 | C14: =Rechenkern!D65+Rechenkern!D66 -> 3156000 | D14: 0
A15: Kapitaldienst jährlich | B15: =Rechenkern!D37 -> 345370.41 | C15: =Rechenkern!D68 -> 301054.41 | D15: =Rechenkern!D74 -> 228141.43
A16: Netto-Mietertrag jährlich | B16: =Rechenkern!D52 -> 136846.01 | C16: =Rechenkern!D52 -> 136846.01 | D16: =Rechenkern!D73 -> 110123.08 | F16: NBank: gebundene Miete 7,80 €/m² senkt den Ertrag
A17: Kapitaldienstdeckungsgrad | B17: =Rechenkern!D55 -> 0.39622968 | C17: =Rechenkern!D69 -> 0.45455573 | D17: =Rechenkern!D75 -> 0.48269654
A18: Zinssatz KfW 297 / 299 (Annahme realistisch, noch zu bestätigen) | B18: =Annahmen!E40 -> 3 | C18: =Annahmen!E41 -> 3.4
A20: Bewertung: Auch mit den theoretischen Höchstbeträgen bleibt der Deckungsgrad deutlich unter 1,0. Die Finanzierung wird durch Förderung allein nicht tragfähig; Förderung ist keine zugesagte Größe.

Sheet Quellen
A1: Quellen und Abrufdatum (22.10.2026)
A2: Aus der Websuche; offizielle Seiten von KfW und NBank waren aus der Arbeitsumgebung nicht direkt abrufbar (Netzwerksperre), Merkblätter wurden nicht im Volltext gelesen.
A4: Thema | B4: Quelle | C4: Aussage und Vorbehalt
A5: KfW 297/298 | B5: https://baukostenplan.de/ratgeber/kfw-297-298-klimafreundlicher-neubau-2026; https://baumentor.de/klimafreundlicher-neubau-kfw-programm-neubaufoerderung/; https://hausbaujournal.com/hausbau-planen/kfw-297-298-klimafreundlicher-neubau/ | C5: 100.000 € je WE, 150.000 € mit QNG-PLUS/-PREMIUM; Zinsangaben widersprüchlich (0,6 % März 2026; 1,96 % laut Quelle vom 01.10.2026; 3,05 % EH 40 laut Drittseite, KfW 29.09.2026); Effizienzhaus-55-Stufe bis 31.12.2026. Zinsen noch zu bestätigen.
A6: KfW 296 | B6: https://www.kfw.de/PDF/Download-Center/F%C3%B6rderprogramme-(Inlandsf%C3%B6rderung)/PDF-Dokumente/6000005195_M_296.pdf; https://baukostenplan.de/ratgeber/kfw-296-klimafreundlicher-neubau-niedrigpreissegment | C6: bis 100.000 € je WE, mindestens EH 55, Wohnflächenoptimierung, nicht kombinierbar mit 297/298/299 je Einheit. Merkblatt nicht im Volltext gelesen.
A7: KfW 299 | B7: https://www.kfw.de/PDF/Download-Center/F%C3%B6rderprogramme-(Inlandsf%C3%B6rderung)/PDF-Dokumente/6000005052_M_299.pdf; https://www.fensterversand.com/foerderung/kfw/299.php | C7: Höchstbeträge je m² laut Drittseite 1.000/1.500/2.000 €; Merkblatt Fassung 07/2026; Zinssatz nicht gefunden.
A8: NBank Wohnraumförderung | B8: https://www.nbank.de/Service/Presse/Niedersachsen-stellt-soziale-Wohnraumf%C3%B6rderung-neu-auf/; https://www.nbank.de/medien/nb-media/Downloads/Programminformation/Produktinformationen/Produktinformation-Energetisch-hochwertiger-Mietwohnungsneubau-in-Mehrfamilienh%C3%A4usern.pdf | C8: Neufassung seit 01.07.2026, Zuschuss bis 40 % der förderfähigen Kosten; Bindung 35 Jahre; Mieten und Kostengrenzen Stand 04/2026 evtl. überholt.
A9: Wohnungsmieten Werlte/Emsland | B9: https://www.kleinanzeigen.de/s-werlte-/2-zimmer-wohnung/k0l13476; https://www.immowelt.de/suche/mieten/wohnung/niedersachsen/werlte-49757/ad08de1969; https://www.immobilienscout24.de/immobilienpreise/niedersachsen/emsland-kreis/mietspiegel; https://www.miet-check.de/mietspiegel/kreis/emsland/; https://www.miete-aktuell.de/mietspiegel/Werlte/Werlte/ | C9: Angebote Neubau 9,5–12,5 €/m²; Durchschnitt Werlte 7,78–8,43 €/m²; Stichprobe klein, Angebotsmieten.
A10: Büromieten | B10: https://www.immowelt.de/suche/mieten/praxis-bueros/niedersachsen/werlte-49757/ad08de1969; https://www.immobilienscout24.de/gewerbe-flaechen/de/niedersachsen/emsland-kreis/buero-mieten/ | C10: Werlte 9,6–12 €/m² (kleine Einheiten), Meppen 9–9,5, Sögel 6,3–7,8; Angebotspreise.
A11: Gastronomie-Pacht | B11: https://gastro-master.de/de/blog/pachtkalkulation-restaurant-berechnen; https://kanzlei-herfurtner.de/gewerbemiete-umsatzmiete-mindestmiete/ | C11: Mietquote 8–12 % vom Nettoumsatz als Richtwert (Ratgeber); keine regionalen Gastro-Flächenmieten gefunden.
A12: Baukosten | B12: https://baukostenplan.de/haustypen/mehrfamilienhaus; https://baukostenplan.de/baukosten/niedersachsen | C12: MFH ca. 2.500–3.500 €/m² Wohnfläche (Ratgeber, nicht BKI); BKI-Regionalfaktor Niedersachsen nicht geprüft.
A13: Zinsen | B13: https://www.baufi24.de/presse/pressemitteilungen/zinskommentar-102026/; https://www.sparkasse.de/pk/ratgeber/wohnen/immobilie-erwerben/bauzinsen.html; https://www.interhyp.de/zinsen/ | C13: 10 Jahre fest Oktober 2026 ca. 4,0–4,5 %; Durchschnitt Baufi24 September 4,16 %.

Sheet Rechenkern
A1: Rechenkern
A2: Jede Spalte ist ein vollständiger Rechenfall. Parameter kommen aus Annahmen (Szenario-Nr. 1 vorsichtig, 2 realistisch, 3 günstig); Zeilen 5–11 sind Fall-Einstellungen.
A4: Größe | B4: Einheit | C4: V 20 % | D4: R 20 % | E4: G 20 % | F4: V 0 % | G4: V 10 % | H4: V 30 % | I4: R 0 % | J4: R 10 % | K4: R 30 % | L4: G 0 % | M4: G 10 % | N4: G 30 % | O4: R 20 %, Tilgung 1 % | P4: R Baukosten +10 % | Q4: R Baukosten +20 % | R4: R Zins +1 pp | S4: R Zins +2 pp | T4: R Leerstand +5 pp | U4: R Leerstand +10 pp | V4: R Miete −10 %
A5: Szenario-Nr. | C5: 1 | D5: 2 | E5: 3 | F5: 1 | G5: 1 | H5: 1 | I5: 2 | J5: 2 | K5: 2 | L5: 3 | M5: 3 | N5: 3 | O5: 2 | P5: 2 | Q5: 2 | R5: 2 | S5: 2 | T5: 2 | U5: 2 | V5: 2
A6: Eigenkapitalquote | B6: % | C6: 0.2 | D6: 0.2 | E6: 0.2 | F6: 0 | G6: 0.1 | H6: 0.3 | I6: 0 | J6: 0.1 | K6: 0.3 | L6: 0 | M6: 0.1 | N6: 0.3 | O6: 0.2 | P6: 0.2 | Q6: 0.2 | R6: 0.2 | S6: 0.2 | T6: 0.2 | U6: 0.2 | V6: 0.2
A7: Faktor Baukosten | C7: 1 | D7: 1 | E7: 1 | F7: 1 | G7: 1 | H7: 1 | I7: 1 | J7: 1 | K7: 1 | L7: 1 | M7: 1 | N7: 1 | O7: 1 | P7: 1.1 | Q7: 1.2 | R7: 1 | S7: 1 | T7: 1 | U7: 1 | V7: 1
A8: Zinszuschlag Hausbank | B8: pp | C8: 0 | D8: 0 | E8: 0 | F8: 0 | G8: 0 | H8: 0 | I8: 0 | J8: 0 | K8: 0 | L8: 0 | M8: 0 | N8: 0 | O8: 0 | P8: 0 | Q8: 0 | R8: 1 | S8: 2 | T8: 0 | U8: 0 | V8: 0
A9: Leerstandszuschlag | B9: pp | C9: 0 | D9: 0 | E9: 0 | F9: 0 | G9: 0 | H9: 0 | I9: 0 | J9: 0 | K9: 0 | L9: 0 | M9: 0 | N9: 0 | O9: 0 | P9: 0 | Q9: 0 | R9: 0 | S9: 0 | T9: 5 | U9: 10 | V9: 0
A10: Faktor Mieten | C10: 1 | D10: 1 | E10: 1 | F10: 1 | G10: 1 | H10: 1 | I10: 1 | J10: 1 | K10: 1 | L10: 1 | M10: 1 | N10: 1 | O10: 1 | P10: 1 | Q10: 1 | R10: 1 | S10: 1 | T10: 1 | U10: 1 | V10: 0.9
A11: Tilgung Override (leer = Annahme) | B11: % | O11: 1
A12: Grundstück | B12: € | C12: =INDEX(Annahmen!$D$15:$F$15,C$5)*INDEX(Annahmen!$D$16:$F$16,C$5) -> 220800 | D12: =INDEX(Annahmen!$D$15:$F$15,D$5)*INDEX(Annahmen!$D$16:$F$16,D$5) -> 220800 | E12: =INDEX(Annahmen!$D$15:$F$15,E$5)*INDEX(Annahmen!$D$16:$F$16,E$5) -> 220800 | F12: =INDEX(Annahmen!$D$15:$F$15,F$5)*INDEX(Annahmen!$D$16:$F$16,F$5) -> 220800 | G12: =INDEX(Annahmen!$D$15:$F$15,G$5)*INDEX(Annahmen!$D$16:$F$16,G$5) -> 220800 | H12: =INDEX(Annahmen!$D$15:$F$15,H$5)*INDEX(Annahmen!$D$16:$F$16,H$5) -> 220800 | I12: =INDEX(Annahmen!$D$15:$F$15,I$5)*INDEX(Annahmen!$D$16:$F$16,I$5) -> 220800 | J12: =INDEX(Annahmen!$D$15:$F$15,J$5)*INDEX(Annahmen!$D$16:$F$16,J$5) -> 220800 | ... V12: =INDEX(Annahmen!$D$15:$F$15,V$5)*INDEX(Annahmen!$D$16:$F$16,V$5) -> 220800
A13: Erwerbsnebenkosten (Grunderwerbsteuer, Notar) | B13: € | C13: =C12*(INDEX(Annahmen!$D$17:$F$17,C$5)+INDEX(Annahmen!$D$18:$F$18,C$5))/100 -> 15456 | D13: =D12*(INDEX(Annahmen!$D$17:$F$17,D$5)+INDEX(Annahmen!$D$18:$F$18,D$5))/100 -> 15456 | E13: =E12*(INDEX(Annahmen!$D$17:$F$17,E$5)+INDEX(Annahmen!$D$18:$F$18,E$5))/100 -> 15456 | F13: =F12*(INDEX(Annahmen!$D$17:$F$17,F$5)+INDEX(Annahmen!$D$18:$F$18,F$5))/100 -> 15456 | G13: =G12*(INDEX(Annahmen!$D$17:$F$17,G$5)+INDEX(Annahmen!$D$18:$F$18,G$5))/100 -> 15456 | H13: =H12*(INDEX(Annahmen!$D$17:$F$17,H$5)+INDEX(Annahmen!$D$18:$F$18,H$5))/100 -> 15456 | I13: =I12*(INDEX(Annahmen!$D$17:$F$17,I$5)+INDEX(Annahmen!$D$18:$F$18,I$5))/100 -> 15456 | J13: =J12*(INDEX(Annahmen!$D$17:$F$17,J$5)+INDEX(Annahmen!$D$18:$F$18,J$5))/100 -> 15456 | ... V13: =V12*(INDEX(Annahmen!$D$17:$F$17,V$5)+INDEX(Annahmen!$D$18:$F$18,V$5))/100 -> 15456
A14: KG 100 Grundstück | B14: € | C14: =C12+C13 -> 236256 | D14: =D12+D13 -> 236256 | E14: =E12+E13 -> 236256 | F14: =F12+F13 -> 236256 | G14: =G12+G13 -> 236256 | H14: =H12+H13 -> 236256 | I14: =I12+I13 -> 236256 | J14: =J12+J13 -> 236256 | ... V14: =V12+V13 -> 236256
A15: KG 200 Herrichten und Erschließen | B15: € | C15: =INDEX(Annahmen!$D$20:$F$20,C$5) -> 60000 | D15: =INDEX(Annahmen!$D$20:$F$20,D$5) -> 40000 | E15: =INDEX(Annahmen!$D$20:$F$20,E$5) -> 25000 | F15: =INDEX(Annahmen!$D$20:$F$20,F$5) -> 60000 | G15: =INDEX(Annahmen!$D$20:$F$20,G$5) -> 60000 | H15: =INDEX(Annahmen!$D$20:$F$20,H$5) -> 60000 | I15: =INDEX(Annahmen!$D$20:$F$20,I$5) -> 40000 | J15: =INDEX(Annahmen!$D$20:$F$20,J$5) -> 40000 | ... V15: =INDEX(Annahmen!$D$20:$F$20,V$5) -> 40000
A16: Bruttogrundfläche gesamt | B16: m² | C16: =INDEX(Annahmen!$D$6:$F$6,C$5)+INDEX(Annahmen!$D$7:$F$7,C$5)+INDEX(Annahmen!$D$8:$F$8,C$5) -> 1775.06 | D16: =INDEX(Annahmen!$D$6:$F$6,D$5)+INDEX(Annahmen!$D$7:$F$7,D$5)+INDEX(Annahmen!$D$8:$F$8,D$5) -> 1775.06 | E16: =INDEX(Annahmen!$D$6:$F$6,E$5)+INDEX(Annahmen!$D$7:$F$7,E$5)+INDEX(Annahmen!$D$8:$F$8,E$5) -> 1775.06 | F16: =INDEX(Annahmen!$D$6:$F$6,F$5)+INDEX(Annahmen!$D$7:$F$7,F$5)+INDEX(Annahmen!$D$8:$F$8,F$5) -> 1775.06 | G16: =INDEX(Annahmen!$D$6:$F$6,G$5)+INDEX(Annahmen!$D$7:$F$7,G$5)+INDEX(Annahmen!$D$8:$F$8,G$5) -> 1775.06 | H16: =INDEX(Annahmen!$D$6:$F$6,H$5)+INDEX(Annahmen!$D$7:$F$7,H$5)+INDEX(Annahmen!$D$8:$F$8,H$5) -> 1775.06 | I16: =INDEX(Annahmen!$D$6:$F$6,I$5)+INDEX(Annahmen!$D$7:$F$7,I$5)+INDEX(Annahmen!$D$8:$F$8,I$5) -> 1775.06 | J16: =INDEX(Annahmen!$D$6:$F$6,J$5)+INDEX(Annahmen!$D$7:$F$7,J$5)+INDEX(Annahmen!$D$8:$F$8,J$5) -> 1775.06 | ... V16: =INDEX(Annahmen!$D$6:$F$6,V$5)+INDEX(Annahmen!$D$7:$F$7,V$5)+INDEX(Annahmen!$D$8:$F$8,V$5) -> 1775.06
A17: KG 300+400 Bauwerk inkl. EH-40-Aufschlag | B17: € | C17: =C16*INDEX(Annahmen!$D$21:$F$21,C$5)*C7*(1+INDEX(Annahmen!$D$22:$F$22,C$5)/100) -> 5538187.2 | D17: =D16*INDEX(Annahmen!$D$21:$F$21,D$5)*D7*(1+INDEX(Annahmen!$D$22:$F$22,D$5)/100) -> 4570779.5 | E17: =E16*INDEX(Annahmen!$D$21:$F$21,E$5)*E7*(1+INDEX(Annahmen!$D$22:$F$22,E$5)/100) -> 3983234.6 | F17: =F16*INDEX(Annahmen!$D$21:$F$21,F$5)*F7*(1+INDEX(Annahmen!$D$22:$F$22,F$5)/100) -> 5538187.2 | G17: =G16*INDEX(Annahmen!$D$21:$F$21,G$5)*G7*(1+INDEX(Annahmen!$D$22:$F$22,G$5)/100) -> 5538187.2 | H17: =H16*INDEX(Annahmen!$D$21:$F$21,H$5)*H7*(1+INDEX(Annahmen!$D$22:$F$22,H$5)/100) -> 5538187.2 | I17: =I16*INDEX(Annahmen!$D$21:$F$21,I$5)*I7*(1+INDEX(Annahmen!$D$22:$F$22,I$5)/100) -> 4570779.5 | J17: =J16*INDEX(Annahmen!$D$21:$F$21,J$5)*J7*(1+INDEX(Annahmen!$D$22:$F$22,J$5)/100) -> 4570779.5 | ... V17: =V16*INDEX(Annahmen!$D$21:$F$21,V$5)*V7*(1+INDEX(Annahmen!$D$22:$F$22,V$5)/100) -> 4570779.5
A18: Gewerbe-Ausbau durch Vermieter | B18: € | C18: =INDEX(Annahmen!$D$13:$F$13,C$5)*INDEX(Annahmen!$D$23:$F$23,C$5) -> 151200 | D18: =INDEX(Annahmen!$D$13:$F$13,D$5)*INDEX(Annahmen!$D$23:$F$23,D$5) -> 126000 | E18: =INDEX(Annahmen!$D$13:$F$13,E$5)*INDEX(Annahmen!$D$23:$F$23,E$5) -> 100800 | F18: =INDEX(Annahmen!$D$13:$F$13,F$5)*INDEX(Annahmen!$D$23:$F$23,F$5) -> 151200 | G18: =INDEX(Annahmen!$D$13:$F$13,G$5)*INDEX(Annahmen!$D$23:$F$23,G$5) -> 151200 | H18: =INDEX(Annahmen!$D$13:$F$13,H$5)*INDEX(Annahmen!$D$23:$F$23,H$5) -> 151200 | I18: =INDEX(Annahmen!$D$13:$F$13,I$5)*INDEX(Annahmen!$D$23:$F$23,I$5) -> 126000 | J18: =INDEX(Annahmen!$D$13:$F$13,J$5)*INDEX(Annahmen!$D$23:$F$23,J$5) -> 126000 | ... V18: =INDEX(Annahmen!$D$13:$F$13,V$5)*INDEX(Annahmen!$D$23:$F$23,V$5) -> 126000
A19: KG 500 Außenanlagen, Stellplätze, Terrasse | B19: € | C19: =INDEX(Annahmen!$D$25:$F$25,C$5)*INDEX(Annahmen!$D$24:$F$24,C$5)+INDEX(Annahmen!$D$26:$F$26,C$5) -> 126800 | D19: =INDEX(Annahmen!$D$25:$F$25,D$5)*INDEX(Annahmen!$D$24:$F$24,D$5)+INDEX(Annahmen!$D$26:$F$26,D$5) -> 101440 | E19: =INDEX(Annahmen!$D$25:$F$25,E$5)*INDEX(Annahmen!$D$24:$F$24,E$5)+INDEX(Annahmen!$D$26:$F$26,E$5) -> 79920 | F19: =INDEX(Annahmen!$D$25:$F$25,F$5)*INDEX(Annahmen!$D$24:$F$24,F$5)+INDEX(Annahmen!$D$26:$F$26,F$5) -> 126800 | G19: =INDEX(Annahmen!$D$25:$F$25,G$5)*INDEX(Annahmen!$D$24:$F$24,G$5)+INDEX(Annahmen!$D$26:$F$26,G$5) -> 126800 | H19: =INDEX(Annahmen!$D$25:$F$25,H$5)*INDEX(Annahmen!$D$24:$F$24,H$5)+INDEX(Annahmen!$D$26:$F$26,H$5) -> 126800 | I19: =INDEX(Annahmen!$D$25:$F$25,I$5)*INDEX(Annahmen!$D$24:$F$24,I$5)+INDEX(Annahmen!$D$26:$F$26,I$5) -> 101440 | J19: =INDEX(Annahmen!$D$25:$F$25,J$5)*INDEX(Annahmen!$D$24:$F$24,J$5)+INDEX(Annahmen!$D$26:$F$26,J$5) -> 101440 | ... V19: =INDEX(Annahmen!$D$25:$F$25,V$5)*INDEX(Annahmen!$D$24:$F$24,V$5)+INDEX(Annahmen!$D$26:$F$26,V$5) -> 101440
A20: Summe KG 300–500 | B20: € | C20: =C17+C18+C19 -> 5816187.2 | D20: =D17+D18+D19 -> 4798219.5 | E20: =E17+E18+E19 -> 4163954.6 | F20: =F17+F18+F19 -> 5816187.2 | G20: =G17+G18+G19 -> 5816187.2 | H20: =H17+H18+H19 -> 5816187.2 | I20: =I17+I18+I19 -> 4798219.5 | J20: =J17+J18+J19 -> 4798219.5 | ... V20: =V17+V18+V19 -> 4798219.5
A21: KG 700 Architektur und Objektplanung | B21: € | C21: =C20*INDEX(Annahmen!$D$28:$F$28,C$5)/100 -> 756104.34 | D21: =D20*INDEX(Annahmen!$D$28:$F$28,D$5)/100 -> 575786.34 | E21: =E20*INDEX(Annahmen!$D$28:$F$28,E$5)/100 -> 458035.01 | F21: =F20*INDEX(Annahmen!$D$28:$F$28,F$5)/100 -> 756104.34 | G21: =G20*INDEX(Annahmen!$D$28:$F$28,G$5)/100 -> 756104.34 | H21: =H20*INDEX(Annahmen!$D$28:$F$28,H$5)/100 -> 756104.34 | I21: =I20*INDEX(Annahmen!$D$28:$F$28,I$5)/100 -> 575786.34 | J21: =J20*INDEX(Annahmen!$D$28:$F$28,J$5)/100 -> 575786.34 | ... V21: =V20*INDEX(Annahmen!$D$28:$F$28,V$5)/100 -> 575786.34
A22: KG 700 Fachplaner (Statik, TGA, Brandschutz, Energie, QNG) | B22: € | C22: =C20*INDEX(Annahmen!$D$29:$F$29,C$5)/100 -> 378052.17 | D22: =D20*INDEX(Annahmen!$D$29:$F$29,D$5)/100 -> 263902.07 | E22: =E20*INDEX(Annahmen!$D$29:$F$29,E$5)/100 -> 187377.96 | F22: =F20*INDEX(Annahmen!$D$29:$F$29,F$5)/100 -> 378052.17 | G22: =G20*INDEX(Annahmen!$D$29:$F$29,G$5)/100 -> 378052.17 | H22: =H20*INDEX(Annahmen!$D$29:$F$29,H$5)/100 -> 378052.17 | I22: =I20*INDEX(Annahmen!$D$29:$F$29,I$5)/100 -> 263902.07 | J22: =J20*INDEX(Annahmen!$D$29:$F$29,J$5)/100 -> 263902.07 | ... V22: =V20*INDEX(Annahmen!$D$29:$F$29,V$5)/100 -> 263902.07
A23: KG 700 Genehmigungen, Gutachten, Vermessung | B23: € | C23: =C20*INDEX(Annahmen!$D$30:$F$30,C$5)/100 -> 87242.808 | D23: =D20*INDEX(Annahmen!$D$30:$F$30,D$5)/100 -> 57578.634 | E23: =E20*INDEX(Annahmen!$D$30:$F$30,E$5)/100 -> 41639.546 | F23: =F20*INDEX(Annahmen!$D$30:$F$30,F$5)/100 -> 87242.808 | G23: =G20*INDEX(Annahmen!$D$30:$F$30,G$5)/100 -> 87242.808 | H23: =H20*INDEX(Annahmen!$D$30:$F$30,H$5)/100 -> 87242.808 | I23: =I20*INDEX(Annahmen!$D$30:$F$30,I$5)/100 -> 57578.634 | J23: =J20*INDEX(Annahmen!$D$30:$F$30,J$5)/100 -> 57578.634 | ... V23: =V20*INDEX(Annahmen!$D$30:$F$30,V$5)/100 -> 57578.634
A24: KG 700 Bauleitung, Versicherungen, Sonstiges | B24: € | C24: =C20*INDEX(Annahmen!$D$31:$F$31,C$5)/100 -> 87242.808 | D24: =D20*INDEX(Annahmen!$D$31:$F$31,D$5)/100 -> 57578.634 | E24: =E20*INDEX(Annahmen!$D$31:$F$31,E$5)/100 -> 41639.546 | F24: =F20*INDEX(Annahmen!$D$31:$F$31,F$5)/100 -> 87242.808 | G24: =G20*INDEX(Annahmen!$D$31:$F$31,G$5)/100 -> 87242.808 | H24: =H20*INDEX(Annahmen!$D$31:$F$31,H$5)/100 -> 87242.808 | I24: =I20*INDEX(Annahmen!$D$31:$F$31,I$5)/100 -> 57578.634 | J24: =J20*INDEX(Annahmen!$D$31:$F$31,J$5)/100 -> 57578.634 | ... V24: =V20*INDEX(Annahmen!$D$31:$F$31,V$5)/100 -> 57578.634
A25: Summe KG 700 Baunebenkosten | B25: € | C25: =C21+C22+C23+C24 -> 1308642.1 | D25: =D21+D22+D23+D24 -> 954845.68 | E25: =E21+E22+E23+E24 -> 728692.06 | F25: =F21+F22+F23+F24 -> 1308642.1 | G25: =G21+G22+G23+G24 -> 1308642.1 | H25: =H21+H22+H23+H24 -> 1308642.1 | I25: =I21+I22+I23+I24 -> 954845.68 | J25: =J21+J22+J23+J24 -> 954845.68 | ... V25: =V21+V22+V23+V24 -> 954845.68
A26: Reserve | B26: € | C26: =(C15+C20)*INDEX(Annahmen!$D$32:$F$32,C$5)/100 -> 470094.98 | D26: =(D15+D20)*INDEX(Annahmen!$D$32:$F$32,D$5)/100 -> 290293.17 | E26: =(E15+E20)*INDEX(Annahmen!$D$32:$F$32,E$5)/100 -> 167558.19 | F26: =(F15+F20)*INDEX(Annahmen!$D$32:$F$32,F$5)/100 -> 470094.98 | G26: =(G15+G20)*INDEX(Annahmen!$D$32:$F$32,G$5)/100 -> 470094.98 | H26: =(H15+H20)*INDEX(Annahmen!$D$32:$F$32,H$5)/100 -> 470094.98 | I26: =(I15+I20)*INDEX(Annahmen!$D$32:$F$32,I$5)/100 -> 290293.17 | J26: =(J15+J20)*INDEX(Annahmen!$D$32:$F$32,J$5)/100 -> 290293.17 | ... V26: =(V15+V20)*INDEX(Annahmen!$D$32:$F$32,V$5)/100 -> 290293.17
A27: Kosten ohne Finanzierungskosten | B27: € | C27: =C14+C15+C20+C25+C26 -> 7891180.3 | D27: =D14+D15+D20+D25+D26 -> 6319614.4 | E27: =E14+E15+E20+E25+E26 -> 5321460.9 | F27: =F14+F15+F20+F25+F26 -> 7891180.3 | G27: =G14+G15+G20+G25+G26 -> 7891180.3 | H27: =H14+H15+H20+H25+H26 -> 7891180.3 | I27: =I14+I15+I20+I25+I26 -> 6319614.4 | J27: =J14+J15+J20+J25+J26 -> 6319614.4 | ... V27: =V14+V15+V20+V25+V26 -> 6319614.4
A28: Zinssatz Hausbank | B28: % | C28: =INDEX(Annahmen!$D$39:$F$39,C$5)+C8 -> 4.9 | D28: =INDEX(Annahmen!$D$39:$F$39,D$5)+D8 -> 4.5 | E28: =INDEX(Annahmen!$D$39:$F$39,E$5)+E8 -> 4.1 | F28: =INDEX(Annahmen!$D$39:$F$39,F$5)+F8 -> 4.9 | G28: =INDEX(Annahmen!$D$39:$F$39,G$5)+G8 -> 4.9 | H28: =INDEX(Annahmen!$D$39:$F$39,H$5)+H8 -> 4.9 | I28: =INDEX(Annahmen!$D$39:$F$39,I$5)+I8 -> 4.5 | J28: =INDEX(Annahmen!$D$39:$F$39,J$5)+J8 -> 4.5 | ... V28: =INDEX(Annahmen!$D$39:$F$39,V$5)+V8 -> 4.5
A29: anfängliche Tilgung | B29: % | C29: =IF(C11="",INDEX(Annahmen!$D$42:$F$42,C$5),C11) -> 2 | D29: =IF(D11="",INDEX(Annahmen!$D$42:$F$42,D$5),D11) -> 2 | E29: =IF(E11="",INDEX(Annahmen!$D$42:$F$42,E$5),E11) -> 2 | F29: =IF(F11="",INDEX(Annahmen!$D$42:$F$42,F$5),F11) -> 2 | G29: =IF(G11="",INDEX(Annahmen!$D$42:$F$42,G$5),G11) -> 2 | H29: =IF(H11="",INDEX(Annahmen!$D$42:$F$42,H$5),H11) -> 2 | I29: =IF(I11="",INDEX(Annahmen!$D$42:$F$42,I$5),I11) -> 2 | J29: =IF(J11="",INDEX(Annahmen!$D$42:$F$42,J$5),J11) -> 2 | ... V29: =IF(V11="",INDEX(Annahmen!$D$42:$F$42,V$5),V11) -> 2
A30: Finanzierungskostensatz (Bauzeit, Anlauf, Bearbeitung) je € Kredit | C30: =C28/100*(INDEX(Annahmen!$D$34:$F$34,C$5)/12*INDEX(Annahmen!$D$35:$F$35,C$5)/100+INDEX(Annahmen!$D$36:$F$36,C$5)/12)+INDEX(Annahmen!$D$37:$F$37,C$5)/100 -> 0.077375 | D30: =D28/100*(INDEX(Annahmen!$D$34:$F$34,D$5)/12*INDEX(Annahmen!$D$35:$F$35,D$5)/100+INDEX(Annahmen!$D$36:$F$36,D$5)/12)+INDEX(Annahmen!$D$37:$F$37,D$5)/100 -> 0.060625 | E30: =E28/100*(INDEX(Annahmen!$D$34:$F$34,E$5)/12*INDEX(Annahmen!$D$35:$F$35,E$5)/100+INDEX(Annahmen!$D$36:$F$36,E$5)/12)+INDEX(Annahmen!$D$37:$F$37,E$5)/100 -> 0.045875 | F30: =F28/100*(INDEX(Annahmen!$D$34:$F$34,F$5)/12*INDEX(Annahmen!$D$35:$F$35,F$5)/100+INDEX(Annahmen!$D$36:$F$36,F$5)/12)+INDEX(Annahmen!$D$37:$F$37,F$5)/100 -> 0.077375 | G30: =G28/100*(INDEX(Annahmen!$D$34:$F$34,G$5)/12*INDEX(Annahmen!$D$35:$F$35,G$5)/100+INDEX(Annahmen!$D$36:$F$36,G$5)/12)+INDEX(Annahmen!$D$37:$F$37,G$5)/100 -> 0.077375 | H30: =H28/100*(INDEX(Annahmen!$D$34:$F$34,H$5)/12*INDEX(Annahmen!$D$35:$F$35,H$5)/100+INDEX(Annahmen!$D$36:$F$36,H$5)/12)+INDEX(Annahmen!$D$37:$F$37,H$5)/100 -> 0.077375 | I30: =I28/100*(INDEX(Annahmen!$D$34:$F$34,I$5)/12*INDEX(Annahmen!$D$35:$F$35,I$5)/100+INDEX(Annahmen!$D$36:$F$36,I$5)/12)+INDEX(Annahmen!$D$37:$F$37,I$5)/100 -> 0.060625 | J30: =J28/100*(INDEX(Annahmen!$D$34:$F$34,J$5)/12*INDEX(Annahmen!$D$35:$F$35,J$5)/100+INDEX(Annahmen!$D$36:$F$36,J$5)/12)+INDEX(Annahmen!$D$37:$F$37,J$5)/100 -> 0.060625 | ... V30: =V28/100*(INDEX(Annahmen!$D$34:$F$34,V$5)/12*INDEX(Annahmen!$D$35:$F$35,V$5)/100+INDEX(Annahmen!$D$36:$F$36,V$5)/12)+INDEX(Annahmen!$D$37:$F$37,V$5)/100 -> 0.060625
A31: GESAMTKOSTEN inkl. Finanzierungskosten | B31: € | C31: =C27/(1-(1-C6)*C30) -> 8411875.4 | D31: =D27/(1-(1-D6)*D30) -> 6641738.7 | E31: =E27/(1-(1-E6)*E30) -> 5524199 | F31: =F27/(1-(1-F6)*F30) -> 8552966 | G31: =G27/(1-(1-G6)*G30) -> 8481834 | H31: =H27/(1-(1-H6)*H30) -> 8343061.4 | I31: =I27/(1-(1-I6)*I30) -> 6727467 | J31: =J27/(1-(1-J6)*J30) -> 6684328 | ... V31: =V27/(1-(1-V6)*V30) -> 6641738.7
A32: davon Finanzierungskosten | B32: € | C32: =C31-C27 -> 520695.09 | D32: =D31-D27 -> 322124.33 | E32: =E31-E27 -> 202738.1 | F32: =F31-F27 -> 661785.75 | G32: =G31-G27 -> 590653.72 | H32: =H31-H27 -> 451881.06 | I32: =I31-I27 -> 407852.69 | J32: =J31-J27 -> 364713.65 | ... V32: =V31-V27 -> 322124.33
A33: Fremdkapital | B33: € | C33: =(1-C6)*C31 -> 6729500.3 | D33: =(1-D6)*D31 -> 5313390.9 | E33: =(1-E6)*E31 -> 4419359.2 | F33: =(1-F6)*F31 -> 8552966 | G33: =(1-G6)*G31 -> 7633650.6 | H33: =(1-H6)*H31 -> 5840142.9 | I33: =(1-I6)*I31 -> 6727467 | J33: =(1-J6)*J31 -> 6015895.2 | ... V33: =(1-V6)*V31 -> 5313390.9
A34: Eigenkapital | B34: € | C34: =C6*C31 -> 1682375.1 | D34: =D6*D31 -> 1328347.7 | E34: =E6*E31 -> 1104839.8 | F34: =F6*F31 -> 0 | G34: =G6*G31 -> 848183.4 | H34: =H6*H31 -> 2502918.4 | I34: =I6*I31 -> 0 | J34: =J6*J31 -> 668432.8 | ... V34: =V6*V31 -> 1328347.7
A35: Zinsen Jahr 1 | B35: € | C35: =C33*C28/100 -> 329745.51 | D35: =D33*D28/100 -> 239102.59 | E35: =E33*E28/100 -> 181193.73 | F35: =F33*F28/100 -> 419095.34 | G35: =G33*G28/100 -> 374048.88 | H35: =H33*H28/100 -> 286167 | I35: =I33*I28/100 -> 302736.02 | J35: =J33*J28/100 -> 270715.28 | ... V35: =V33*V28/100 -> 239102.59
A36: Tilgung Jahr 1 | B36: € | C36: =C33*C29/100 -> 134590.01 | D36: =D33*D29/100 -> 106267.82 | E36: =E33*E29/100 -> 88387.184 | F36: =F33*F29/100 -> 171059.32 | G36: =G33*G29/100 -> 152673.01 | H36: =H33*H29/100 -> 116802.86 | I36: =I33*I29/100 -> 134549.34 | J36: =J33*J29/100 -> 120317.9 | ... V36: =V33*V29/100 -> 106267.82
A37: Kapitaldienst jährlich | B37: € | C37: =C35+C36 -> 464335.52 | D37: =D35+D36 -> 345370.41 | E37: =E35+E36 -> 269580.91 | F37: =F35+F36 -> 590154.66 | G37: =G35+G36 -> 526721.89 | H37: =H35+H36 -> 402969.86 | I37: =I35+I36 -> 437285.36 | J37: =J35+J36 -> 391033.19 | ... V37: =V35+V36 -> 345370.41
A38: Kreditrate monatlich | B38: € | C38: =C37/12 -> 38694.627 | D38: =D37/12 -> 28780.868 | E38: =E37/12 -> 22465.076 | F38: =F37/12 -> 49179.555 | G38: =G37/12 -> 43893.491 | H38: =H37/12 -> 33580.822 | I38: =I37/12 -> 36440.446 | J38: =J37/12 -> 32586.099 | ... V38: =V37/12 -> 28780.868
A39: Zinsbelastung monatlich | B39: € | C39: =C35/12 -> 27478.793 | D39: =D35/12 -> 19925.216 | E39: =E35/12 -> 15099.477 | F39: =F35/12 -> 34924.611 | G39: =G35/12 -> 31170.74 | H39: =H35/12 -> 23847.25 | I39: =I35/12 -> 25228.001 | J39: =J35/12 -> 22559.607 | ... V39: =V35/12 -> 19925.216
A40: Sollmiete Wohnen jährlich | B40: € | C40: =INDEX(Annahmen!$D$9:$F$9,C$5)*INDEX(Annahmen!$D$44:$F$44,C$5)*C10*12 -> 96436.02 | D40: =INDEX(Annahmen!$D$9:$F$9,D$5)*INDEX(Annahmen!$D$44:$F$44,D$5)*D10*12 -> 106587.18 | E40: =INDEX(Annahmen!$D$9:$F$9,E$5)*INDEX(Annahmen!$D$44:$F$44,E$5)*E10*12 -> 116738.34 | F40: =INDEX(Annahmen!$D$9:$F$9,F$5)*INDEX(Annahmen!$D$44:$F$44,F$5)*F10*12 -> 96436.02 | G40: =INDEX(Annahmen!$D$9:$F$9,G$5)*INDEX(Annahmen!$D$44:$F$44,G$5)*G10*12 -> 96436.02 | H40: =INDEX(Annahmen!$D$9:$F$9,H$5)*INDEX(Annahmen!$D$44:$F$44,H$5)*H10*12 -> 96436.02 | I40: =INDEX(Annahmen!$D$9:$F$9,I$5)*INDEX(Annahmen!$D$44:$F$44,I$5)*I10*12 -> 106587.18 | J40: =INDEX(Annahmen!$D$9:$F$9,J$5)*INDEX(Annahmen!$D$44:$F$44,J$5)*J10*12 -> 106587.18 | ... V40: =INDEX(Annahmen!$D$9:$F$9,V$5)*INDEX(Annahmen!$D$44:$F$44,V$5)*V10*12 -> 95928.462
A41: Sollmiete Gastronomie jährlich | B41: € | C41: =INDEX(Annahmen!$D$11:$F$11,C$5)*INDEX(Annahmen!$D$46:$F$46,C$5)*C10*12 -> 42240 | D41: =INDEX(Annahmen!$D$11:$F$11,D$5)*INDEX(Annahmen!$D$46:$F$46,D$5)*D10*12 -> 52800 | E41: =INDEX(Annahmen!$D$11:$F$11,E$5)*INDEX(Annahmen!$D$46:$F$46,E$5)*E10*12 -> 63360 | F41: =INDEX(Annahmen!$D$11:$F$11,F$5)*INDEX(Annahmen!$D$46:$F$46,F$5)*F10*12 -> 42240 | G41: =INDEX(Annahmen!$D$11:$F$11,G$5)*INDEX(Annahmen!$D$46:$F$46,G$5)*G10*12 -> 42240 | H41: =INDEX(Annahmen!$D$11:$F$11,H$5)*INDEX(Annahmen!$D$46:$F$46,H$5)*H10*12 -> 42240 | I41: =INDEX(Annahmen!$D$11:$F$11,I$5)*INDEX(Annahmen!$D$46:$F$46,I$5)*I10*12 -> 52800 | J41: =INDEX(Annahmen!$D$11:$F$11,J$5)*INDEX(Annahmen!$D$46:$F$46,J$5)*J10*12 -> 52800 | ... V41: =INDEX(Annahmen!$D$11:$F$11,V$5)*INDEX(Annahmen!$D$46:$F$46,V$5)*V10*12 -> 47520
A42: Sollmiete Büros jährlich | B42: € | C42: =INDEX(Annahmen!$D$12:$F$12,C$5)*INDEX(Annahmen!$D$48:$F$48,C$5)*C10*12 -> 5744.64 | D42: =INDEX(Annahmen!$D$12:$F$12,D$5)*INDEX(Annahmen!$D$48:$F$48,D$5)*D10*12 -> 6420.48 | E42: =INDEX(Annahmen!$D$12:$F$12,E$5)*INDEX(Annahmen!$D$48:$F$48,E$5)*E10*12 -> 7096.32 | F42: =INDEX(Annahmen!$D$12:$F$12,F$5)*INDEX(Annahmen!$D$48:$F$48,F$5)*F10*12 -> 5744.64 | G42: =INDEX(Annahmen!$D$12:$F$12,G$5)*INDEX(Annahmen!$D$48:$F$48,G$5)*G10*12 -> 5744.64 | H42: =INDEX(Annahmen!$D$12:$F$12,H$5)*INDEX(Annahmen!$D$48:$F$48,H$5)*H10*12 -> 5744.64 | I42: =INDEX(Annahmen!$D$12:$F$12,I$5)*INDEX(Annahmen!$D$48:$F$48,I$5)*I10*12 -> 6420.48 | J42: =INDEX(Annahmen!$D$12:$F$12,J$5)*INDEX(Annahmen!$D$48:$F$48,J$5)*J10*12 -> 6420.48 | ... V42: =INDEX(Annahmen!$D$12:$F$12,V$5)*INDEX(Annahmen!$D$48:$F$48,V$5)*V10*12 -> 5778.432
A43: Sollmiete gesamt jährlich | B43: € | C43: =C40+C41+C42 -> 144420.66 | D43: =D40+D41+D42 -> 165807.66 | E43: =E40+E41+E42 -> 187194.66 | F43: =F40+F41+F42 -> 144420.66 | G43: =G40+G41+G42 -> 144420.66 | H43: =H40+H41+H42 -> 144420.66 | I43: =I40+I41+I42 -> 165807.66 | J43: =J40+J41+J42 -> 165807.66 | ... V43: =V40+V41+V42 -> 149226.89
A44: Mieteinnahmen Wohnen nach Leerstand | B44: € | C44: =C40*(1-(INDEX(Annahmen!$D$45:$F$45,C$5)+C9)/100) -> 92578.579 | D44: =D40*(1-(INDEX(Annahmen!$D$45:$F$45,D$5)+D9)/100) -> 103922.5 | E44: =E40*(1-(INDEX(Annahmen!$D$45:$F$45,E$5)+E9)/100) -> 114987.26 | F44: =F40*(1-(INDEX(Annahmen!$D$45:$F$45,F$5)+F9)/100) -> 92578.579 | G44: =G40*(1-(INDEX(Annahmen!$D$45:$F$45,G$5)+G9)/100) -> 92578.579 | H44: =H40*(1-(INDEX(Annahmen!$D$45:$F$45,H$5)+H9)/100) -> 92578.579 | I44: =I40*(1-(INDEX(Annahmen!$D$45:$F$45,I$5)+I9)/100) -> 103922.5 | J44: =J40*(1-(INDEX(Annahmen!$D$45:$F$45,J$5)+J9)/100) -> 103922.5 | ... V44: =V40*(1-(INDEX(Annahmen!$D$45:$F$45,V$5)+V9)/100) -> 93530.25
A45: Mieteinnahmen Gastronomie nach Ausfall | B45: € | C45: =C41*(1-(INDEX(Annahmen!$D$47:$F$47,C$5)+C9)/100) -> 38860.8 | D45: =D41*(1-(INDEX(Annahmen!$D$47:$F$47,D$5)+D9)/100) -> 50160 | E45: =E41*(1-(INDEX(Annahmen!$D$47:$F$47,E$5)+E9)/100) -> 61459.2 | F45: =F41*(1-(INDEX(Annahmen!$D$47:$F$47,F$5)+F9)/100) -> 38860.8 | G45: =G41*(1-(INDEX(Annahmen!$D$47:$F$47,G$5)+G9)/100) -> 38860.8 | H45: =H41*(1-(INDEX(Annahmen!$D$47:$F$47,H$5)+H9)/100) -> 38860.8 | I45: =I41*(1-(INDEX(Annahmen!$D$47:$F$47,I$5)+I9)/100) -> 50160 | J45: =J41*(1-(INDEX(Annahmen!$D$47:$F$47,J$5)+J9)/100) -> 50160 | ... V45: =V41*(1-(INDEX(Annahmen!$D$47:$F$47,V$5)+V9)/100) -> 45144
A46: Mieteinnahmen Büros nach Leerstand | B46: € | C46: =C42*(1-(INDEX(Annahmen!$D$49:$F$49,C$5)+C9)/100) -> 4595.712 | D46: =D42*(1-(INDEX(Annahmen!$D$49:$F$49,D$5)+D9)/100) -> 5650.0224 | E46: =E42*(1-(INDEX(Annahmen!$D$49:$F$49,E$5)+E9)/100) -> 6528.6144 | F46: =F42*(1-(INDEX(Annahmen!$D$49:$F$49,F$5)+F9)/100) -> 4595.712 | G46: =G42*(1-(INDEX(Annahmen!$D$49:$F$49,G$5)+G9)/100) -> 4595.712 | H46: =H42*(1-(INDEX(Annahmen!$D$49:$F$49,H$5)+H9)/100) -> 4595.712 | I46: =I42*(1-(INDEX(Annahmen!$D$49:$F$49,I$5)+I9)/100) -> 5650.0224 | J46: =J42*(1-(INDEX(Annahmen!$D$49:$F$49,J$5)+J9)/100) -> 5650.0224 | ... V46: =V42*(1-(INDEX(Annahmen!$D$49:$F$49,V$5)+V9)/100) -> 5085.0202
A47: Mieteinnahmen gesamt nach Leerstand | B47: € | C47: =C44+C45+C46 -> 136035.09 | D47: =D44+D45+D46 -> 159732.52 | E47: =E44+E45+E46 -> 182975.08 | F47: =F44+F45+F46 -> 136035.09 | G47: =G44+G45+G46 -> 136035.09 | H47: =H44+H45+H46 -> 136035.09 | I47: =I44+I45+I46 -> 159732.52 | J47: =J44+J45+J46 -> 159732.52 | ... V47: =V44+V45+V46 -> 143759.27
A48: nicht umlagefähige Kosten Wohnen | B48: € | C48: =INDEX(Annahmen!$D$9:$F$9,C$5)*INDEX(Annahmen!$D$51:$F$51,C$5)+INDEX(Annahmen!$D$10:$F$10,C$5)*INDEX(Annahmen!$D$52:$F$52,C$5)+INDEX(Annahmen!$D$9:$F$9,C$5)*INDEX(Annahmen!$D$53:$F$53,C$5) -> 20826.74 | D48: =INDEX(Annahmen!$D$9:$F$9,D$5)*INDEX(Annahmen!$D$51:$F$51,D$5)+INDEX(Annahmen!$D$10:$F$10,D$5)*INDEX(Annahmen!$D$52:$F$52,D$5)+INDEX(Annahmen!$D$9:$F$9,D$5)*INDEX(Annahmen!$D$53:$F$53,D$5) -> 16643.02 | E48: =INDEX(Annahmen!$D$9:$F$9,E$5)*INDEX(Annahmen!$D$51:$F$51,E$5)+INDEX(Annahmen!$D$10:$F$10,E$5)*INDEX(Annahmen!$D$52:$F$52,E$5)+INDEX(Annahmen!$D$9:$F$9,E$5)*INDEX(Annahmen!$D$53:$F$53,E$5) -> 14151.16 | F48: =INDEX(Annahmen!$D$9:$F$9,F$5)*INDEX(Annahmen!$D$51:$F$51,F$5)+INDEX(Annahmen!$D$10:$F$10,F$5)*INDEX(Annahmen!$D$52:$F$52,F$5)+INDEX(Annahmen!$D$9:$F$9,F$5)*INDEX(Annahmen!$D$53:$F$53,F$5) -> 20826.74 | G48: =INDEX(Annahmen!$D$9:$F$9,G$5)*INDEX(Annahmen!$D$51:$F$51,G$5)+INDEX(Annahmen!$D$10:$F$10,G$5)*INDEX(Annahmen!$D$52:$F$52,G$5)+INDEX(Annahmen!$D$9:$F$9,G$5)*INDEX(Annahmen!$D$53:$F$53,G$5) -> 20826.74 | H48: =INDEX(Annahmen!$D$9:$F$9,H$5)*INDEX(Annahmen!$D$51:$F$51,H$5)+INDEX(Annahmen!$D$10:$F$10,H$5)*INDEX(Annahmen!$D$52:$F$52,H$5)+INDEX(Annahmen!$D$9:$F$9,H$5)*INDEX(Annahmen!$D$53:$F$53,H$5) -> 20826.74 | I48: =INDEX(Annahmen!$D$9:$F$9,I$5)*INDEX(Annahmen!$D$51:$F$51,I$5)+INDEX(Annahmen!$D$10:$F$10,I$5)*INDEX(Annahmen!$D$52:$F$52,I$5)+INDEX(Annahmen!$D$9:$F$9,I$5)*INDEX(Annahmen!$D$53:$F$53,I$5) -> 16643.02 | J48: =INDEX(Annahmen!$D$9:$F$9,J$5)*INDEX(Annahmen!$D$51:$F$51,J$5)+INDEX(Annahmen!$D$10:$F$10,J$5)*INDEX(Annahmen!$D$52:$F$52,J$5)+INDEX(Annahmen!$D$9:$F$9,J$5)*INDEX(Annahmen!$D$53:$F$53,J$5) -> 16643.02 | ... V48: =INDEX(Annahmen!$D$9:$F$9,V$5)*INDEX(Annahmen!$D$51:$F$51,V$5)+INDEX(Annahmen!$D$10:$F$10,V$5)*INDEX(Annahmen!$D$52:$F$52,V$5)+INDEX(Annahmen!$D$9:$F$9,V$5)*INDEX(Annahmen!$D$53:$F$53,V$5) -> 16643.02
A49: Instandhaltung und sonstige Kosten Gewerbe | B49: € | C49: =(INDEX(Annahmen!$D$11:$F$11,C$5)+INDEX(Annahmen!$D$12:$F$12,C$5))*(INDEX(Annahmen!$D$54:$F$54,C$5)+INDEX(Annahmen!$D$56:$F$56,C$5)) -> 5955.84 | D49: =(INDEX(Annahmen!$D$11:$F$11,D$5)+INDEX(Annahmen!$D$12:$F$12,D$5))*(INDEX(Annahmen!$D$54:$F$54,D$5)+INDEX(Annahmen!$D$56:$F$56,D$5)) -> 4466.88 | E49: =(INDEX(Annahmen!$D$11:$F$11,E$5)+INDEX(Annahmen!$D$12:$F$12,E$5))*(INDEX(Annahmen!$D$54:$F$54,E$5)+INDEX(Annahmen!$D$56:$F$56,E$5)) -> 3474.24 | F49: =(INDEX(Annahmen!$D$11:$F$11,F$5)+INDEX(Annahmen!$D$12:$F$12,F$5))*(INDEX(Annahmen!$D$54:$F$54,F$5)+INDEX(Annahmen!$D$56:$F$56,F$5)) -> 5955.84 | G49: =(INDEX(Annahmen!$D$11:$F$11,G$5)+INDEX(Annahmen!$D$12:$F$12,G$5))*(INDEX(Annahmen!$D$54:$F$54,G$5)+INDEX(Annahmen!$D$56:$F$56,G$5)) -> 5955.84 | H49: =(INDEX(Annahmen!$D$11:$F$11,H$5)+INDEX(Annahmen!$D$12:$F$12,H$5))*(INDEX(Annahmen!$D$54:$F$54,H$5)+INDEX(Annahmen!$D$56:$F$56,H$5)) -> 5955.84 | I49: =(INDEX(Annahmen!$D$11:$F$11,I$5)+INDEX(Annahmen!$D$12:$F$12,I$5))*(INDEX(Annahmen!$D$54:$F$54,I$5)+INDEX(Annahmen!$D$56:$F$56,I$5)) -> 4466.88 | J49: =(INDEX(Annahmen!$D$11:$F$11,J$5)+INDEX(Annahmen!$D$12:$F$12,J$5))*(INDEX(Annahmen!$D$54:$F$54,J$5)+INDEX(Annahmen!$D$56:$F$56,J$5)) -> 4466.88 | ... V49: =(INDEX(Annahmen!$D$11:$F$11,V$5)+INDEX(Annahmen!$D$12:$F$12,V$5))*(INDEX(Annahmen!$D$54:$F$54,V$5)+INDEX(Annahmen!$D$56:$F$56,V$5)) -> 4466.88
A50: Verwaltung Gewerbe | B50: € | C50: =(C41+C42)*INDEX(Annahmen!$D$55:$F$55,C$5)/100 -> 1919.3856 | D50: =(D41+D42)*INDEX(Annahmen!$D$55:$F$55,D$5)/100 -> 1776.6144 | E50: =(E41+E42)*INDEX(Annahmen!$D$55:$F$55,E$5)/100 -> 1761.408 | F50: =(F41+F42)*INDEX(Annahmen!$D$55:$F$55,F$5)/100 -> 1919.3856 | G50: =(G41+G42)*INDEX(Annahmen!$D$55:$F$55,G$5)/100 -> 1919.3856 | H50: =(H41+H42)*INDEX(Annahmen!$D$55:$F$55,H$5)/100 -> 1919.3856 | I50: =(I41+I42)*INDEX(Annahmen!$D$55:$F$55,I$5)/100 -> 1776.6144 | J50: =(J41+J42)*INDEX(Annahmen!$D$55:$F$55,J$5)/100 -> 1776.6144 | ... V50: =(V41+V42)*INDEX(Annahmen!$D$55:$F$55,V$5)/100 -> 1598.953
A51: laufende Kosten gesamt | B51: € | C51: =C48+C49+C50 -> 28701.966 | D51: =D48+D49+D50 -> 22886.514 | E51: =E48+E49+E50 -> 19386.808 | F51: =F48+F49+F50 -> 28701.966 | G51: =G48+G49+G50 -> 28701.966 | H51: =H48+H49+H50 -> 28701.966 | I51: =I48+I49+I50 -> 22886.514 | J51: =J48+J49+J50 -> 22886.514 | ... V51: =V48+V49+V50 -> 22708.853
A52: NETTO-MIETERTRAG (vor Kapitaldienst) | B52: € | C52: =C47-C51 -> 107333.13 | D52: =D47-D51 -> 136846.01 | E52: =E47-E51 -> 163588.27 | F52: =F47-F51 -> 107333.13 | G52: =G47-G51 -> 107333.13 | H52: =H47-H51 -> 107333.13 | I52: =I47-I51 -> 136846.01 | J52: =J47-J51 -> 136846.01 | ... V52: =V47-V51 -> 121050.42
A53: Cashflow nach Kapitaldienst jährlich | B53: € | C53: =C52-C37 -> -357002.4 | D53: =D52-D37 -> -208524.4 | E53: =E52-E37 -> -105992.64 | F53: =F52-F37 -> -482821.53 | G53: =G52-G37 -> -419388.77 | H53: =H52-H37 -> -295636.74 | I53: =I52-I37 -> -300439.35 | J53: =J52-J37 -> -254187.18 | ... V53: =V52-V37 -> -224319.99
A54: Cashflow nach Kapitaldienst monatlich | B54: € | C54: =C53/12 -> -29750.2 | D54: =D53/12 -> -17377.034 | E54: =E53/12 -> -8832.72 | F54: =F53/12 -> -40235.128 | G54: =G53/12 -> -34949.064 | H54: =H53/12 -> -24636.395 | I54: =I53/12 -> -25036.612 | J54: =J53/12 -> -21182.265 | ... V54: =V53/12 -> -18693.333
A55: KAPITALDIENSTDECKUNGSGRAD | B55: x | C55: =C52/C37 -> 0.23115424 | D55: =D52/D37 -> 0.39622968 | E55: =E52/E37 -> 0.60682439 | F55: =F52/F37 -> 0.18187288 | G55: =G52/G37 -> 0.20377571 | H55: =H52/H37 -> 0.26635522 | I55: =I52/I37 -> 0.31294441 | J55: =J52/J37 -> 0.34996009 | ... V55: =V52/V37 -> 0.35049447
A56: Nettoanfangsrendite auf Gesamtkosten | B56: % | C56: =C52/C31 -> 0.012759714 | D56: =D52/D31 -> 0.020603944 | E56: =E52/E31 -> 0.02961303 | F56: =F52/F31 -> 0.012549229 | G56: =G52/G31 -> 0.012654471 | H56: =H52/H31 -> 0.012864957 | I56: =I52/I31 -> 0.020341387 | J56: =J52/J31 -> 0.020472665 | ... V56: =V52/V31 -> 0.018225712
A57: Break-even Wohnmiete für DSCR 1,0 (übrige Mieten unverändert) | B57: €/m² | C57: =(1*C37-(C52-C44))/(INDEX(Annahmen!$D$9:$F$9,C$5)*12*(1-(INDEX(Annahmen!$D$45:$F$45,C$5)+C9)/100)) -> 46.13399 | D57: =(1*D37-(D52-D44))/(INDEX(Annahmen!$D$9:$F$9,D$5)*12*(1-(INDEX(Annahmen!$D$45:$F$45,D$5)+D9)/100)) -> 31.568645 | E57: =(1*E37-(E52-E44))/(INDEX(Annahmen!$D$9:$F$9,E$5)*12*(1-(INDEX(Annahmen!$D$45:$F$45,E$5)+E9)/100)) -> 22.100438 | F57: =(1*F37-(F52-F44))/(INDEX(Annahmen!$D$9:$F$9,F$5)*12*(1-(INDEX(Annahmen!$D$45:$F$45,F$5)+F9)/100)) -> 59.044987 | G57: =(1*G37-(G52-G44))/(INDEX(Annahmen!$D$9:$F$9,G$5)*12*(1-(INDEX(Annahmen!$D$45:$F$45,G$5)+G9)/100)) -> 52.535801 | H57: =(1*H37-(H52-H44))/(INDEX(Annahmen!$D$9:$F$9,H$5)*12*(1-(INDEX(Annahmen!$D$45:$F$45,H$5)+H9)/100)) -> 39.836921 | I57: =(1*I37-(I52-I44))/(INDEX(Annahmen!$D$9:$F$9,I$5)*12*(1-(INDEX(Annahmen!$D$45:$F$45,I$5)+I9)/100)) -> 40.855439 | J57: =(1*J37-(J52-J44))/(INDEX(Annahmen!$D$9:$F$9,J$5)*12*(1-(INDEX(Annahmen!$D$45:$F$45,J$5)+J9)/100)) -> 36.182267 | ... V57: =(1*V37-(V52-V44))/(INDEX(Annahmen!$D$9:$F$9,V$5)*12*(1-(INDEX(Annahmen!$D$45:$F$45,V$5)+V9)/100)) -> 32.114581
A58: Break-even Wohnmiete für DSCR 1,2 | B58: €/m² | C58: =(1.2*C37-(C52-C44))/(INDEX(Annahmen!$D$9:$F$9,C$5)*12*(1-(INDEX(Annahmen!$D$45:$F$45,C$5)+C9)/100)) -> 55.663597 | D58: =(1.2*D37-(D52-D44))/(INDEX(Annahmen!$D$9:$F$9,D$5)*12*(1-(INDEX(Annahmen!$D$45:$F$45,D$5)+D9)/100)) -> 38.547671 | E58: =(1.2*E37-(E52-E44))/(INDEX(Annahmen!$D$9:$F$9,E$5)*12*(1-(INDEX(Annahmen!$D$45:$F$45,E$5)+E9)/100)) -> 27.492653 | F58: =(1.2*F37-(F52-F44))/(INDEX(Annahmen!$D$9:$F$9,F$5)*12*(1-(INDEX(Annahmen!$D$45:$F$45,F$5)+F9)/100)) -> 71.156794 | G58: =(1.2*G37-(G52-G44))/(INDEX(Annahmen!$D$9:$F$9,G$5)*12*(1-(INDEX(Annahmen!$D$45:$F$45,G$5)+G9)/100)) -> 63.34577 | H58: =(1.2*H37-(H52-H44))/(INDEX(Annahmen!$D$9:$F$9,H$5)*12*(1-(INDEX(Annahmen!$D$45:$F$45,H$5)+H9)/100)) -> 48.107114 | I58: =(1.2*I37-(I52-I44))/(INDEX(Annahmen!$D$9:$F$9,I$5)*12*(1-(INDEX(Annahmen!$D$45:$F$45,I$5)+I9)/100)) -> 49.691825 | J58: =(1.2*J37-(J52-J44))/(INDEX(Annahmen!$D$9:$F$9,J$5)*12*(1-(INDEX(Annahmen!$D$45:$F$45,J$5)+J9)/100)) -> 44.084018 | ... V58: =(1.2*V37-(V52-V44))/(INDEX(Annahmen!$D$9:$F$9,V$5)*12*(1-(INDEX(Annahmen!$D$45:$F$45,V$5)+V9)/100)) -> 39.093607
A59: Break-even Mietfaktor (alle Mieten) für DSCR 1,0 | B59: x | C59: =(1*C37+C48+C49)/(C47-C50) -> 3.6618985 | D59: =(1*D37+D48+D49)/(D47-D50) -> 2.3201431 | E59: =(1*E37+E48+E49)/(E47-E50) -> 1.5849042 | F59: =(1*F37+F48+F49)/(F47-F50) -> 4.6000372 | G59: =(1*G37+G48+G49)/(G47-G50) -> 4.1270668 | H59: =(1*H37+H48+H49)/(H47-H50) -> 3.2043409 | I59: =(1*I37+I48+I49)/(I47-I50) -> 2.9020457 | J59: =(1*J37+J48+J49)/(J47-J50) -> 2.6092287 | ... V59: =(1*V37+V48+V49)/(V47-V50) -> 2.5779368
A60: Break-even Mietfaktor (alle Mieten) für DSCR 1,2 | B60: x | C60: =(1.2*C37+C48+C49)/(C47-C50) -> 4.3543387 | D60: =(1.2*D37+D48+D49)/(D47-D50) -> 2.7574429 | E60: =(1.2*E37+E48+E49)/(E47-E50) -> 1.8824324 | F60: =(1.2*F37+F48+F49)/(F47-F50) -> 5.4801051 | G60: =(1.2*G37+G48+G49)/(G47-G50) -> 4.9125406 | H60: =(1.2*H37+H48+H49)/(H47-H50) -> 3.8052696 | I60: =(1.2*I37+I48+I49)/(I47-I50) -> 3.4557259 | J60: =(1.2*J37+J48+J49)/(J47-J50) -> 3.1043456 | ... V60: =(1.2*V37+V48+V49)/(V47-V50) -> 3.0638254
A61: Fremdkapital, das bei DSCR 1,2 tragbar wäre | B61: € | C61: =C52/(1.2*(C28+C29)/100) -> 1296293.8 | D61: =D52/(1.2*(D28+D29)/100) -> 1754436 | E61: =E52/(1.2*(E28+E29)/100) -> 2234812.4 | F61: =F52/(1.2*(F28+F29)/100) -> 1296293.8 | G61: =G52/(1.2*(G28+G29)/100) -> 1296293.8 | H61: =H52/(1.2*(H28+H29)/100) -> 1296293.8 | I61: =I52/(1.2*(I28+I29)/100) -> 1754436 | J61: =J52/(1.2*(J28+J29)/100) -> 1754436 | ... V61: =V52/(1.2*(V28+V29)/100) -> 1551928.4
A62: dafür nötige Eigenkapitalquote | B62: % | C62: =1-C61/(C27+C61*C30) -> 0.83779054 | D62: =1-D61/(D27+D61*D30) -> 0.72697755 | E62: =1-E61/(E27+E61*E30) -> 0.58797576 | F62: =1-F61/(F27+F61*F30) -> 0.83779054 | G62: =1-G61/(G27+G61*G30) -> 0.83779054 | H62: =1-H61/(H27+H61*H30) -> 0.83779054 | I62: =1-I61/(I27+I61*I30) -> 0.72697755 | J62: =1-J61/(J27+J61*J30) -> 0.72697755 | ... V62: =1-V61/(V27+V61*V30) -> 0.75802915
A63: dafür nötiges Eigenkapital | B63: € | C63: =C27/(1-(1-C62)*C30)-C61 -> 6695187.2 | D63: =D27/(1-(1-D62)*D30)-D61 -> 4671541 | E63: =E27/(1-(1-E62)*E30)-E61 -> 3189170.5 | F63: =F27/(1-(1-F62)*F30)-F61 -> 6695187.2 | G63: =G27/(1-(1-G62)*G30)-G61 -> 6695187.2 | H63: =H27/(1-(1-H62)*H30)-H61 -> 6695187.2 | I63: =I27/(1-(1-I62)*I30)-I61 -> 4671541 | J63: =J27/(1-(1-J62)*J30)-J61 -> 4671541 | ... V63: =V27/(1-(1-V62)*V30)-V61 -> 4861771.6
A64: Wohnanteil der Bruttogeschossfläche (Wohnen + EG-Kern) | B64: % | C64: =(INDEX(Annahmen!$D$7:$F$7,C$5)+INDEX(Annahmen!$D$8:$F$8,C$5)+INDEX(Annahmen!$D$6:$F$6,C$5)-INDEX(Annahmen!$D$13:$F$13,C$5))/C16 -> 0.71606594 | D64: =(INDEX(Annahmen!$D$7:$F$7,D$5)+INDEX(Annahmen!$D$8:$F$8,D$5)+INDEX(Annahmen!$D$6:$F$6,D$5)-INDEX(Annahmen!$D$13:$F$13,D$5))/D16 -> 0.71606594 | E64: =(INDEX(Annahmen!$D$7:$F$7,E$5)+INDEX(Annahmen!$D$8:$F$8,E$5)+INDEX(Annahmen!$D$6:$F$6,E$5)-INDEX(Annahmen!$D$13:$F$13,E$5))/E16 -> 0.71606594 | F64: =(INDEX(Annahmen!$D$7:$F$7,F$5)+INDEX(Annahmen!$D$8:$F$8,F$5)+INDEX(Annahmen!$D$6:$F$6,F$5)-INDEX(Annahmen!$D$13:$F$13,F$5))/F16 -> 0.71606594 | G64: =(INDEX(Annahmen!$D$7:$F$7,G$5)+INDEX(Annahmen!$D$8:$F$8,G$5)+INDEX(Annahmen!$D$6:$F$6,G$5)-INDEX(Annahmen!$D$13:$F$13,G$5))/G16 -> 0.71606594 | H64: =(INDEX(Annahmen!$D$7:$F$7,H$5)+INDEX(Annahmen!$D$8:$F$8,H$5)+INDEX(Annahmen!$D$6:$F$6,H$5)-INDEX(Annahmen!$D$13:$F$13,H$5))/H16 -> 0.71606594 | I64: =(INDEX(Annahmen!$D$7:$F$7,I$5)+INDEX(Annahmen!$D$8:$F$8,I$5)+INDEX(Annahmen!$D$6:$F$6,I$5)-INDEX(Annahmen!$D$13:$F$13,I$5))/I16 -> 0.71606594 | J64: =(INDEX(Annahmen!$D$7:$F$7,J$5)+INDEX(Annahmen!$D$8:$F$8,J$5)+INDEX(Annahmen!$D$6:$F$6,J$5)-INDEX(Annahmen!$D$13:$F$13,J$5))/J16 -> 0.71606594 | ... V64: =(INDEX(Annahmen!$D$7:$F$7,V$5)+INDEX(Annahmen!$D$8:$F$8,V$5)+INDEX(Annahmen!$D$6:$F$6,V$5)-INDEX(Annahmen!$D$13:$F$13,V$5))/V16 -> 0.71606594
A65: KfW 297/298: theoretischer Kredit | B65: € | C65: =MIN(INDEX(Annahmen!$D$10:$F$10,C$5)*INDEX(Annahmen!$D$58:$F$58,C$5),C64*C33) -> 2400000 | D65: =MIN(INDEX(Annahmen!$D$10:$F$10,D$5)*INDEX(Annahmen!$D$58:$F$58,D$5),D64*D33) -> 2400000 | E65: =MIN(INDEX(Annahmen!$D$10:$F$10,E$5)*INDEX(Annahmen!$D$58:$F$58,E$5),E64*E33) -> 2400000 | F65: =MIN(INDEX(Annahmen!$D$10:$F$10,F$5)*INDEX(Annahmen!$D$58:$F$58,F$5),F64*F33) -> 2400000 | G65: =MIN(INDEX(Annahmen!$D$10:$F$10,G$5)*INDEX(Annahmen!$D$58:$F$58,G$5),G64*G33) -> 2400000 | H65: =MIN(INDEX(Annahmen!$D$10:$F$10,H$5)*INDEX(Annahmen!$D$58:$F$58,H$5),H64*H33) -> 2400000 | I65: =MIN(INDEX(Annahmen!$D$10:$F$10,I$5)*INDEX(Annahmen!$D$58:$F$58,I$5),I64*I33) -> 2400000 | J65: =MIN(INDEX(Annahmen!$D$10:$F$10,J$5)*INDEX(Annahmen!$D$58:$F$58,J$5),J64*J33) -> 2400000 | ... V65: =MIN(INDEX(Annahmen!$D$10:$F$10,V$5)*INDEX(Annahmen!$D$58:$F$58,V$5),V64*V33) -> 2400000
A66: KfW 299: theoretischer Kredit | B66: € | C66: =MIN(INDEX(Annahmen!$D$13:$F$13,C$5)*INDEX(Annahmen!$D$59:$F$59,C$5),(1-C64)*C33) -> 756000 | D66: =MIN(INDEX(Annahmen!$D$13:$F$13,D$5)*INDEX(Annahmen!$D$59:$F$59,D$5),(1-D64)*D33) -> 756000 | E66: =MIN(INDEX(Annahmen!$D$13:$F$13,E$5)*INDEX(Annahmen!$D$59:$F$59,E$5),(1-E64)*E33) -> 756000 | F66: =MIN(INDEX(Annahmen!$D$13:$F$13,F$5)*INDEX(Annahmen!$D$59:$F$59,F$5),(1-F64)*F33) -> 756000 | G66: =MIN(INDEX(Annahmen!$D$13:$F$13,G$5)*INDEX(Annahmen!$D$59:$F$59,G$5),(1-G64)*G33) -> 756000 | H66: =MIN(INDEX(Annahmen!$D$13:$F$13,H$5)*INDEX(Annahmen!$D$59:$F$59,H$5),(1-H64)*H33) -> 756000 | I66: =MIN(INDEX(Annahmen!$D$13:$F$13,I$5)*INDEX(Annahmen!$D$59:$F$59,I$5),(1-I64)*I33) -> 756000 | J66: =MIN(INDEX(Annahmen!$D$13:$F$13,J$5)*INDEX(Annahmen!$D$59:$F$59,J$5),(1-J64)*J33) -> 756000 | ... V66: =MIN(INDEX(Annahmen!$D$13:$F$13,V$5)*INDEX(Annahmen!$D$59:$F$59,V$5),(1-V64)*V33) -> 756000
A67: Hausbank-Anteil | B67: € | C67: =C33-C65-C66 -> 3573500.3 | D67: =D33-D65-D66 -> 2157390.9 | E67: =E33-E65-E66 -> 1263359.2 | F67: =F33-F65-F66 -> 5396966 | G67: =G33-G65-G66 -> 4477650.6 | H67: =H33-H65-H66 -> 2684142.9 | I67: =I33-I65-I66 -> 3571467 | J67: =J33-J65-J66 -> 2859895.2 | ... V67: =V33-V65-V66 -> 2157390.9
A68: Kapitaldienst mit KfW (theoretisch) | B68: € | C68: =C65*(INDEX(Annahmen!$D$40:$F$40,C$5)+C29)/100+C66*(INDEX(Annahmen!$D$41:$F$41,C$5)+C29)/100+C67*(C28+C29)/100 -> 423175.52 | D68: =D65*(INDEX(Annahmen!$D$40:$F$40,D$5)+D29)/100+D66*(INDEX(Annahmen!$D$41:$F$41,D$5)+D29)/100+D67*(D28+D29)/100 -> 301054.41 | E68: =E65*(INDEX(Annahmen!$D$40:$F$40,E$5)+E29)/100+E66*(INDEX(Annahmen!$D$41:$F$41,E$5)+E29)/100+E67*(E28+E29)/100 -> 207840.91 | F68: =F65*(INDEX(Annahmen!$D$40:$F$40,F$5)+F29)/100+F66*(INDEX(Annahmen!$D$41:$F$41,F$5)+F29)/100+F67*(F28+F29)/100 -> 548994.66 | G68: =G65*(INDEX(Annahmen!$D$40:$F$40,G$5)+G29)/100+G66*(INDEX(Annahmen!$D$41:$F$41,G$5)+G29)/100+G67*(G28+G29)/100 -> 485561.89 | H68: =H65*(INDEX(Annahmen!$D$40:$F$40,H$5)+H29)/100+H66*(INDEX(Annahmen!$D$41:$F$41,H$5)+H29)/100+H67*(H28+H29)/100 -> 361809.86 | I68: =I65*(INDEX(Annahmen!$D$40:$F$40,I$5)+I29)/100+I66*(INDEX(Annahmen!$D$41:$F$41,I$5)+I29)/100+I67*(I28+I29)/100 -> 392969.36 | J68: =J65*(INDEX(Annahmen!$D$40:$F$40,J$5)+J29)/100+J66*(INDEX(Annahmen!$D$41:$F$41,J$5)+J29)/100+J67*(J28+J29)/100 -> 346717.19 | ... V68: =V65*(INDEX(Annahmen!$D$40:$F$40,V$5)+V29)/100+V66*(INDEX(Annahmen!$D$41:$F$41,V$5)+V29)/100+V67*(V28+V29)/100 -> 301054.41
A69: DSCR mit KfW (theoretisch, nicht bestätigt) | B69: x | C69: =C52/C68 -> 0.25363737 | D69: =D52/D68 -> 0.45455573 | E69: =E52/E68 -> 0.78708408 | F69: =F52/F68 -> 0.19550851 | G69: =G52/G68 -> 0.22104932 | H69: =H52/H68 -> 0.29665616 | I69: =I52/I68 -> 0.34823583 | J69: =J52/J68 -> 0.39469058 | ... V69: =V52/V68 -> 0.40208817
A70: Cashflow mit KfW jährlich | B70: € | C70: =C52-C68 -> -315842.4 | D70: =D52-D68 -> -164208.4 | E70: =E52-E68 -> -44252.639 | F70: =F52-F68 -> -441661.53 | G70: =G52-G68 -> -378228.77 | H70: =H52-H68 -> -254476.74 | I70: =I52-I68 -> -256123.35 | J70: =J52-J68 -> -209871.18 | ... V70: =V52-V68 -> -180003.99
A71: NBank-Zuschuss (Obergrenze 40 %, nicht zugesagt) | B71: € | C71: =INDEX(Annahmen!$D$60:$F$60,C$5)/100*MIN(C64*C27,INDEX(Annahmen!$D$62:$F$62,C$5)*INDEX(Annahmen!$D$9:$F$9,C$5)) -> 1803522.8 | D71: =INDEX(Annahmen!$D$60:$F$60,D$5)/100*MIN(D64*D27,INDEX(Annahmen!$D$62:$F$62,D$5)*INDEX(Annahmen!$D$9:$F$9,D$5)) -> 1803522.8 | E71: =INDEX(Annahmen!$D$60:$F$60,E$5)/100*MIN(E64*E27,INDEX(Annahmen!$D$62:$F$62,E$5)*INDEX(Annahmen!$D$9:$F$9,E$5)) -> 1524206.7 | F71: =INDEX(Annahmen!$D$60:$F$60,F$5)/100*MIN(F64*F27,INDEX(Annahmen!$D$62:$F$62,F$5)*INDEX(Annahmen!$D$9:$F$9,F$5)) -> 1803522.8 | G71: =INDEX(Annahmen!$D$60:$F$60,G$5)/100*MIN(G64*G27,INDEX(Annahmen!$D$62:$F$62,G$5)*INDEX(Annahmen!$D$9:$F$9,G$5)) -> 1803522.8 | H71: =INDEX(Annahmen!$D$60:$F$60,H$5)/100*MIN(H64*H27,INDEX(Annahmen!$D$62:$F$62,H$5)*INDEX(Annahmen!$D$9:$F$9,H$5)) -> 1803522.8 | I71: =INDEX(Annahmen!$D$60:$F$60,I$5)/100*MIN(I64*I27,INDEX(Annahmen!$D$62:$F$62,I$5)*INDEX(Annahmen!$D$9:$F$9,I$5)) -> 1803522.8 | J71: =INDEX(Annahmen!$D$60:$F$60,J$5)/100*MIN(J64*J27,INDEX(Annahmen!$D$62:$F$62,J$5)*INDEX(Annahmen!$D$9:$F$9,J$5)) -> 1803522.8 | ... V71: =INDEX(Annahmen!$D$60:$F$60,V$5)/100*MIN(V64*V27,INDEX(Annahmen!$D$62:$F$62,V$5)*INDEX(Annahmen!$D$9:$F$9,V$5)) -> 1803522.8
A72: Fremdkapital nach Zuschuss | B72: € | C72: =C33-C71 -> 4925977.5 | D72: =D33-D71 -> 3509868.2 | E72: =E33-E71 -> 2895152.4 | F72: =F33-F71 -> 6749443.3 | G72: =G33-G71 -> 5830127.9 | H72: =H33-H71 -> 4036620.2 | I72: =I33-I71 -> 4923944.3 | J72: =J33-J71 -> 4212372.4 | ... V72: =V33-V71 -> 3509868.2
A73: Netto-Mietertrag bei gebundener Miete | B73: € | C73: =C52-C44+INDEX(Annahmen!$D$9:$F$9,C$5)*INDEX(Annahmen!$D$61:$F$61,C$5)*12*(1-INDEX(Annahmen!$D$45:$F$45,C$5)/100) -> 90766.432 | D73: =D52-D44+INDEX(Annahmen!$D$9:$F$9,D$5)*INDEX(Annahmen!$D$61:$F$61,D$5)*12*(1-INDEX(Annahmen!$D$45:$F$45,D$5)/100) -> 110123.08 | E73: =E52-E44+INDEX(Annahmen!$D$9:$F$9,E$5)*INDEX(Annahmen!$D$61:$F$61,E$5)*12*(1-INDEX(Annahmen!$D$45:$F$45,E$5)/100) -> 126592.37 | F73: =F52-F44+INDEX(Annahmen!$D$9:$F$9,F$5)*INDEX(Annahmen!$D$61:$F$61,F$5)*12*(1-INDEX(Annahmen!$D$45:$F$45,F$5)/100) -> 90766.432 | G73: =G52-G44+INDEX(Annahmen!$D$9:$F$9,G$5)*INDEX(Annahmen!$D$61:$F$61,G$5)*12*(1-INDEX(Annahmen!$D$45:$F$45,G$5)/100) -> 90766.432 | H73: =H52-H44+INDEX(Annahmen!$D$9:$F$9,H$5)*INDEX(Annahmen!$D$61:$F$61,H$5)*12*(1-INDEX(Annahmen!$D$45:$F$45,H$5)/100) -> 90766.432 | I73: =I52-I44+INDEX(Annahmen!$D$9:$F$9,I$5)*INDEX(Annahmen!$D$61:$F$61,I$5)*12*(1-INDEX(Annahmen!$D$45:$F$45,I$5)/100) -> 110123.08 | J73: =J52-J44+INDEX(Annahmen!$D$9:$F$9,J$5)*INDEX(Annahmen!$D$61:$F$61,J$5)*12*(1-INDEX(Annahmen!$D$45:$F$45,J$5)/100) -> 110123.08 | ... V73: =V52-V44+INDEX(Annahmen!$D$9:$F$9,V$5)*INDEX(Annahmen!$D$61:$F$61,V$5)*12*(1-INDEX(Annahmen!$D$45:$F$45,V$5)/100) -> 104719.74
A74: Kapitaldienst nach Zuschuss | B74: € | C74: =C72*(C28+C29)/100 -> 339892.45 | D74: =D72*(D28+D29)/100 -> 228141.43 | E74: =E72*(E28+E29)/100 -> 176604.3 | F74: =F72*(F28+F29)/100 -> 465711.59 | G74: =G72*(G28+G29)/100 -> 402278.82 | H74: =H72*(H28+H29)/100 -> 278526.79 | I74: =I72*(I28+I29)/100 -> 320056.38 | J74: =J72*(J28+J29)/100 -> 273804.21 | ... V74: =V72*(V28+V29)/100 -> 228141.43
A75: DSCR mit NBank-Zuschuss (theoretisch) | B75: x | C75: =C73/C74 -> 0.26704457 | D75: =D73/D74 -> 0.48269654 | E75: =E73/E74 -> 0.71681363 | F75: =F73/F74 -> 0.19489838 | G75: =G73/G74 -> 0.22563065 | H75: =H73/H74 -> 0.32588043 | I75: =I73/I74 -> 0.344074 | J75: =J73/J74 -> 0.40219645 | ... V75: =V73/V74 -> 0.45901237

Sheet Prüfung
A1: Plausibilitäts- und Konsistenzprüfung
A2: Alle Prüfungen müssen WAHR sein.
A4: Prüfung | B4: Wert A | C4: Wert B | D4: OK
A5: Gesamtkosten = Σ Kostengruppen (R 20 %) | B5: =Rechenkern!D31 -> 6641738.7 | C5: =Rechenkern!D14+Rechenkern!D15+Rechenkern!D20+Rechenkern!D25+Rechenkern!D26+Rechenkern!D32 -> 6641738.7 | D5: =ABS(B5-C5)<0.01 -> TRUE
A6: Eigenkapital + Fremdkapital = Gesamtkosten (R 20 %) | B6: =Rechenkern!D34+Rechenkern!D33 -> 6641738.7 | C6: =Rechenkern!D31 -> 6641738.7 | D6: =ABS(B6-C6)<0.01 -> TRUE
A7: Wohnfläche Flächenblatt = Annahme | B7: =Flächen!E21 -> 845.9264 | C7: =Annahmen!E9 -> 845.93 | D7: =ABS(B7-C7)<0.01 -> TRUE
A8: Kapitaldienst = Zinsen + Tilgung (R 20 %) | B8: =Rechenkern!D37 -> 345370.41 | C8: =Rechenkern!D35+Rechenkern!D36 -> 345370.41 | D8: =ABS(B8-C8)<0.01 -> TRUE
A9: Netto-Mietertrag = Einnahmen − Kosten (R 20 %) | B9: =Rechenkern!D52 -> 136846.01 | C9: =Rechenkern!D47-Rechenkern!D51 -> 136846.01 | D9: =ABS(B9-C9)<0.01 -> TRUE
A10: Break-even Wohnmiete liefert DSCR 1,0 (R 20 %) | B10: =Rechenkern!D52-Rechenkern!D44+Annahmen!E9*Rechenkern!D57*12*(1-Annahmen!E45/100) -> 345370.41 | C10: =Rechenkern!D37 -> 345370.41 | D10: =ABS(B10-C10)<0.01 -> TRUE
A12: Alle Prüfungen bestanden | D12: =AND(D5:D10) -> TRUE
